Workbook

Sheet Dashboard
B2: Mozaik Design — Enterprise Sales Funnel
B3: As of 16 Apr 2026 · values in EUR (€)
B5: Open opportunities | C5: Gross pipeline | D5: Weighted pipeline | E5: Avg deal size
B6: =COUNTA(Opportunities!C2:C108) -> 107 | C6: =SUM(Opportunities!D2:D108) -> 12872043 | D6: =SUMPRODUCT(IFERROR(Opportunities!D2:D108*Opportunities!F2:F108,0)) -> 6946629.5 | E6: =IFERROR(SUM(Opportunities!D2:D108)/COUNT(Opportunities!D2:D108),0) -> 171627.24
B9: Pipeline by Stage
A10: Stage | B10: # Deals | C10: Gross € | D10: Weighted € | E10: Avg Prob. | F10: Avg Deal €
B11: TOFU | C11: =COUNTIF(Opportunities!A2:A108,"TOFU") -> 44 | D11: =SUMIF(Opportunities!A2:A108,"TOFU",Opportunities!D2:D108) -> 1159000 | E11: =SUMPRODUCT((Opportunities!A2:A108="TOFU")*IFERROR(Opportunities!D2:D108*Opportunities!F2:F108,0)) -> 231800 | F11: =IFERROR(AVERAGEIFS(Opportunities!F2:F108,Opportunities!A2:A108,"TOFU"),0) -> 0.56421053 | G11: =IFERROR(AVERAGEIFS(Opportunities!D2:D108,Opportunities!A2:A108,"TOFU"),0) -> 68176.471
B12: MOFU | C12: =COUNTIF(Opportunities!A2:A108,"MOFU") -> 30 | D12: =SUMIF(Opportunities!A2:A108,"MOFU",Opportunities!D2:D108) -> 4063280 | E12: =SUMPRODUCT((Opportunities!A2:A108="MOFU")*IFERROR(Opportunities!D2:D108*Opportunities!F2:F108,0)) -> 1828054 | F12: =IFERROR(AVERAGEIFS(Opportunities!F2:F108,Opportunities!A2:A108,"MOFU"),0) -> 0.44703704 | G12: =IFERROR(AVERAGEIFS(Opportunities!D2:D108,Opportunities!A2:A108,"MOFU"),0) -> 162531.2
B13: BOFU | C13: =COUNTIF(Opportunities!A2:A108,"BOFU") -> 33 | D13: =SUMIF(Opportunities!A2:A108,"BOFU",Opportunities!D2:D108) -> 7649763 | E13: =SUMPRODUCT((Opportunities!A2:A108="BOFU")*IFERROR(Opportunities!D2:D108*Opportunities!F2:F108,0)) -> 4886775.5 | F13: =IFERROR(AVERAGEIFS(Opportunities!F2:F108,Opportunities!A2:A108,"BOFU"),0) -> 0.68272727 | G13: =IFERROR(AVERAGEIFS(Opportunities!D2:D108,Opportunities!A2:A108,"BOFU"),0) -> 231811
B14: TOTAL | C14: =SUM(C11:C13) -> 107 | D14: =SUM(D11:D13) -> 12872043 | E14: =SUM(E11:E13) -> 6946629.5 | G14: =IFERROR(D14/C14,0) -> 120299.47
B17: Pipeline by Rep
A18: Rep | B18: # Deals | C18: Gross € | D18: Weighted € | E18: TOFU | F18: MOFU | G18: BOFU
B19: Burçin | C19: =COUNTIF(Opportunities!B2:B108,"Burçin") -> 35 | D19: =SUMIF(Opportunities!B2:B108,"Burçin",Opportunities!D2:D108) -> 2469530 | E19: =SUMPRODUCT((Opportunities!B2:B108="Burçin")*IFERROR(Opportunities!D2:D108*Opportunities!F2:F108,0)) -> 1640966.5 | F19: =COUNTIFS(Opportunities!B2:B108,"Burçin",Opportunities!A2:A108,"TOFU") -> 19 | G19: =COUNTIFS(Opportunities!B2:B108,"Burçin",Opportunities!A2:A108,"MOFU") -> 8 | H19: =COUNTIFS(Opportunities!B2:B108,"Burçin",Opportunities!A2:A108,"BOFU") -> 8
B20: Zeynep | C20: =COUNTIF(Opportunities!B2:B108,"Zeynep") -> 28 | D20: =SUMIF(Opportunities!B2:B108,"Zeynep",Opportunities!D2:D108) -> 5977700 | E20: =SUMPRODUCT((Opportunities!B2:B108="Zeynep")*IFERROR(Opportunities!D2:D108*Opportunities!F2:F108,0)) -> 3869530 | F20: =COUNTIFS(Opportunities!B2:B108,"Zeynep",Opportunities!A2:A108,"TOFU") -> 13 | G20: =COUNTIFS(Opportunities!B2:B108,"Zeynep",Opportunities!A2:A108,"MOFU") -> 5 | H20: =COUNTIFS(Opportunities!B2:B108,"Zeynep",Opportunities!A2:A108,"BOFU") -> 10
B21: İrem | C21: =COUNTIF(Opportunities!B2:B108,"İrem") -> 29 | D21: =SUMIF(Opportunities!B2:B108,"İrem",Opportunities!D2:D108) -> 2540000 | E21: =SUMPRODUCT((Opportunities!B2:B108="İrem")*IFERROR(Opportunities!D2:D108*Opportunities!F2:F108,0)) -> 879700 | F21: =COUNTIFS(Opportunities!B2:B108,"İrem",Opportunities!A2:A108,"TOFU") -> 6 | G21: =COUNTIFS(Opportunities!B2:B108,"İrem",Opportunities!A2:A108,"MOFU") -> 13 | H21: =COUNTIFS(Opportunities!B2:B108,"İrem",Opportunities!A2:A108,"BOFU") -> 10
B22: Elif | C22: =COUNTIF(Opportunities!B2:B108,"Elif") -> 15 | D22: =SUMIF(Opportunities!B2:B108,"Elif",Opportunities!D2:D108) -> 1884813 | E22: =SUMPRODUCT((Opportunities!B2:B108="Elif")*IFERROR(Opportunities!D2:D108*Opportunities!F2:F108,0)) -> 556433.01 | F22: =COUNTIFS(Opportunities!B2:B108,"Elif",Opportunities!A2:A108,"TOFU") -> 6 | G22: =COUNTIFS(Opportunities!B2:B108,"Elif",Opportunities!A2:A108,"MOFU") -> 4 | H22: =COUNTIFS(Opportunities!B2:B108,"Elif",Opportunities!A2:A108,"BOFU") -> 5
B25: Qualification Field Fill Rate
A26: Field | B26: Filled | C26: Yes | D26: No | E26: Fill %
B27: Proposal Sent | C27: =COUNTIF(Opportunities!H2:H108,"Yes")+COUNTIF(Opportunities!H2:H108,"No") -> 88 | D27: =COUNTIF(Opportunities!H2:H108,"Yes") -> 54 | E27: =COUNTIF(Opportunities!H2:H108,"No") -> 34 | F27: =IFERROR(C27/COUNTA(Opportunities!H2:H108),0) -> 0.82242991
B28: Architect Engaged | C28: =COUNTIF(Opportunities!I2:I108,"Yes")+COUNTIF(Opportunities!I2:I108,"No") -> 83 | D28: =COUNTIF(Opportunities!I2:I108,"Yes") -> 70 | E28: =COUNTIF(Opportunities!I2:I108,"No") -> 13 | F28: =IFERROR(C28/COUNTA(Opportunities!I2:I108),0) -> 0.77570093
B29: Budget Confirmed | C29: =COUNTIF(Opportunities!J2:J108,"Yes")+COUNTIF(Opportunities!J2:J108,"No") -> 71 | D29: =COUNTIF(Opportunities!J2:J108,"Yes") -> 37 | E29: =COUNTIF(Opportunities!J2:J108,"No") -> 34 | F29: =IFERROR(C29/COUNTA(Opportunities!J2:J108),0) -> 0.6635514
B30: Decision Maker | C30: =COUNTIF(Opportunities!K2:K108,"Yes")+COUNTIF(Opportunities!K2:K108,"No") -> 75 | D30: =COUNTIF(Opportunities!K2:K108,"Yes") -> 65 | E30: =COUNTIF(Opportunities!K2:K108,"No") -> 10 | F30: =IFERROR(C30/COUNTA(Opportunities!K2:K108),0) -> 0.70093458
B31: Competitor Present | C31: =COUNTIF(Opportunities!L2:L108,"Yes")+COUNTIF(Opportunities!L2:L108,"No") -> 68 | D31: =COUNTIF(Opportunities!L2:L108,"Yes") -> 43 | E31: =COUNTIF(Opportunities!L2:L108,"No") -> 25 | F31: =IFERROR(C31/COUNTA(Opportunities!L2:L108),0) -> 0.63551402
B34: Where to read next
B35: • Opportunities tab — all 107 open deals, filterable by rep / stage / probability. • Definitions tab — what TOFU / MOFU / BOFU mean for Mozaik. • Outbound tab — 40 architect targets. • Data Quality tab — what's missing & why it blocks forecasting. • CRM Schema tab — fields you need before migrating to a CRM.

Sheet Opportunities
A1: Stage | B1: Rep | C1: Project | D1: Value (€) | E1: Close Date | F1: Probability | G1: Weighted (€) | H1: Proposal Sent | I1: Architect Engaged | J1: Budget Confirmed | K1: Decision Maker | L1: Competitor Present | M1: Architect Firm | N1: Next Step | O1: Data Fill (5)
A2: BOFU | B2: Zeynep | C2: Borsa İstanbul – Çalışma Sandalye/toplantı | D2: 1000000 | E2: 2026-03-30 00:00:00 | F2: 0.85 | G2: =IFERROR(D2*F2,"") -> 850000 | H2: Yes | I2: Yes | J2: Yes | K2: Yes | L2: Yes | N2: son onay | O2: =COUNTIF(H2:L2,"Yes")+COUNTIF(H2:L2,"No") -> 5
A3: BOFU | B3: Burçin | C3: Hillside Bodrum | D3: 1200000 | E3: 2027-05-15 00:00:00 | F3: 0.55 | G3: =IFERROR(D3*F3,"") -> 660000 | H3: Yes | I3: Yes | J3: Unknown | K3: Yes | L3: Yes | N3: sıkı takip !!! perş toplantı | O3: =COUNTIF(H3:L3,"Yes")+COUNTIF(H3:L3,"No") -> 4
A4: BOFU | B4: Zeynep | C4: Borsa İstanbulYönetim | D4: 900000 | E4: 2026-04-30 00:00:00 | F4: 0.7 | G4: =IFERROR(D4*F4,"") -> 630000 | H4: Yes | I4: Yes | J4: Unknown | K4: Yes | L4: Yes | N4: revize teklif aşaması | O4: =COUNTIF(H4:L4,"Yes")+COUNTIF(H4:L4,"No") -> 4
A5: BOFU | B5: Zeynep | C5: GARANTİ SOFTWORK | D5: 458000 | E5: mid april | F5: 0.85 | G5: =IFERROR(D5*F5,"") -> 389300 | H5: Yes | I5: Yes | J5: Yes | K5: Yes | L5: No | N5: çok istediklerini belirttiler | O5: =COUNTIF(H5:L5,"Yes")+COUNTIF(H5:L5,"No") -> 5
A6: BOFU | B6: Zeynep | C6: DaaX – 2nd Package | D6: 448000 | E6: beginning of april | F6: 0.8 | G6: =IFERROR(D6*F6,"") -> 358400 | H6: Yes | I6: Yes | J6: Yes | K6: Yes | L6: Yes | N6: ONAY BEKLENİYOR | O6: =COUNTIF(H6:L6,"Yes")+COUNTIF(H6:L6,"No") -> 5
A7: BOFU | B7: Burçin | C7: Divan Talya – Upsell (Ek Paket) | D7: 328000 | E7: 2026-04-06 00:00:00 | F7: 1 | G7: =IFERROR(D7*F7,"") -> 328000 | H7: Yes | I7: Yes | J7: Yes | K7: Yes | L7: Yes | N7: onaylandı, sipariş girildi. ödeme bekleniyor | O7: =COUNTIF(H7:L7,"Yes")+COUNTIF(H7:L7,"No") -> 5
A8: BOFU | B8: Elif | C8: Numarine (VIP) | D8: 279000 | E8: 2026-04-10 00:00:00 | F8: 1 | G8: =IFERROR(D8*F8,"") -> 279000 | H8: Yes | I8: Yes | J8: Yes | K8: Yes | L8: No | N8: ONAYLANDI | O8: =COUNTIF(H8:L8,"Yes")+COUNTIF(H8:L8,"No") -> 5
A9: BOFU | B9: Zeynep | C9: amazon framery | D9: 125000 | E9: end of april | F9: 0.9 | G9: =IFERROR(D9*F9,"") -> 112500 | H9: Yes | I9: Yes | J9: Yes | K9: Yes | L9: Yes | N9: revize teklif gitti doalr oalrak onay vakti | O9: =COUNTIF(H9:L9,"Yes")+COUNTIF(H9:L9,"No") -> 5
A10: BOFU | B10: Zeynep | C10: EPIAŞ | D10: 200000 | E10: end of april | F10: 0.5 | G10: =IFERROR(D10*F10,"") -> 100000 | H10: Yes | I10: Yes | J10: No | K10: Yes | L10: Yes | N10: ihaleye çıkılmış takip istiyor | O10: =COUNTIF(H10:L10,"Yes")+COUNTIF(H10:L10,"No") -> 5
A11: BOFU | B11: Zeynep | C11: halkbank | D11: 110000 | E11: end of march | F11: 0.9 | G11: =IFERROR(D11*F11,"") -> 99000 | H11: Yes | I11: Yes | J11: Yes | K11: Yes | L11: No | N11: ONAY BEKLENİYOR | O11: =COUNTIF(H11:L11,"Yes")+COUNTIF(H11:L11,"No") -> 5
A12: BOFU | B12: Burçin | C12: Gençoglu Karakoy satış ofis | D12: 100000 | E12: 2026-03-31 00:00:00 | F12: 0.97 | G12: =IFERROR(D12*F12,"") -> 97000 | H12: Yes | I12: Yes | J12: Yes | K12: Yes | L12: No | N12: onay bekleniyor - imar ! | O12: =COUNTIF(H12:L12,"Yes")+COUNTIF(H12:L12,"No") -> 5
A13: BOFU | B13: Zeynep | C13: 30xp-04 | D13: 105700 | E13: end of march | F13: 0.9 | G13: =IFERROR(D13*F13,"") -> 95130 | H13: Yes | I13: Yes | J13: Yes | K13: Yes | L13: Yes | O13: =COUNTIF(H13:L13,"Yes")+COUNTIF(H13:L13,"No") -> 5
A14: BOFU | B14: İrem | C14: Aylin Koen / Office Renovation | D14: 119000 | F14: 0.75 | G14: =IFERROR(D14*F14,"") -> 89250 | H14: Yes | I14: Yes | J14: Yes | K14: Yes | L14: Yes | N14: 03/03 de teklif verildi. / onay aşamasında | O14: =COUNTIF(H14:L14,"Yes")+COUNTIF(H14:L14,"No") -> 5
A15: BOFU | B15: Zeynep | C15: cevahir holding kavacık teras | D15: 93000 | E15: end of april | F15: 0.9 | G15: =IFERROR(D15*F15,"") -> 83700 | H15: Yes | I15: Yes | J15: Yes | K15: Yes | L15: No | N15: rev teklif | O15: =COUNTIF(H15:L15,"Yes")+COUNTIF(H15:L15,"No") -> 5
A16: BOFU | B16: İrem | C16: Turkcell Ankara Vega Plaza | D16: 415000 | F16: 0.2 | G16: =IFERROR(D16*F16,"") -> 83000 | H16: Yes | I16: Yes | J16: No | K16: Yes | L16: Yes | N16: teklif verildi,bütçe onayına sunuldu | O16: =COUNTIF(H16:L16,"Yes")+COUNTIF(H16:L16,"No") -> 5
A17: BOFU | B17: Elif | C17: Divan Bodrum Padel Club | D17: 130576 | E17: 2026-05-31 00:00:00 | F17: 0.51 | G17: =IFERROR(D17*F17,"") -> 66593.76 | H17: Yes | I17: Yes | J17: Yes | K17: Yes | L17: Yes | N17: yeni teklif | O17: =COUNTIF(H17:L17,"Yes")+COUNTIF(H17:L17,"No") -> 5
A18: BOFU | B18: Burçin | C18: 7Mehmet Restaurant | D18: 70000 | E18: 2026-04-17 00:00:00 | F18: 0.95 | G18: =IFERROR(D18*F18,"") -> 66500 | H18: Yes | I18: Yes | J18: Unknown | K18: Yes | L18: Unknown | N18: mock ürün tekrar sunuma gitti , teslim süresi konusuldu , onay bekleniyor | O18: =COUNTIF(H18:L18,"Yes")+COUNTIF(H18:L18,"No") -> 3
A19: BOFU | B19: Elif | C19: Robert Koleji | D19: 163800 | E19: Ağustos sonu | F19: 0.35 | G19: =IFERROR(D19*F19,"") -> 57330 | H19: Yes | I19: Yes | J19: Yes | K19: Yes | L19: Yes | N19: 15.04 teklif | O19: =COUNTIF(H19:L19,"Yes")+COUNTIF(H19:L19,"No") -> 5
A20: BOFU | B20: Elif | C20: Casino – Kıbrıs (Edra) | D20: 185000 | E20: 2026-04-10 00:00:00 | F20: 0.3 | G20: =IFERROR(D20*F20,"") -> 55500 | H20: Yes | I20: Yes | J20: Unknown | K20: Yes | L20: No | N20: onay bekleniyor | O20: =COUNTIF(H20:L20,"Yes")+COUNTIF(H20:L20,"No") -> 4
A21: BOFU | B21: Zeynep | C21: Garanti – TOPLANTI Sandalye | D21: 78000 | F21: 0.7 | G21: =IFERROR(D21*F21,"") -> 54600 | H21: Yes | I21: Yes | J21: Yes | K21: Yes | L21: Yes | N21: revize teklif aşaması | O21: =COUNTIF(H21:L21,"Yes")+COUNTIF(H21:L21,"No") -> 5
A22: BOFU | B22: Burçin | C22: Fiko Selimiye Otel | D22: 70000 | E22: 2026-04-17 00:00:00 | F22: 0.75 | G22: =IFERROR(D22*F22,"") -> 52500 | H22: Yes | I22: Yes | J22: Unknown | K22: Yes | L22: No | O22: =COUNTIF(H22:L22,"Yes")+COUNTIF(H22:L22,"No") -> 4
A23: BOFU | B23: İrem | C23: Çalık Holding / İstanbloom Office | D23: 90000 | F23: 0.5 | G23: =IFERROR(D23*F23,"") -> 45000 | H23: Yes | I23: Yes | J23: No | K23: Yes | L23: Yes | N23: ihale(firmalara teklif verildi ) | O23: =COUNTIF(H23:L23,"Yes")+COUNTIF(H23:L23,"No") -> 5
A24: BOFU | B24: İrem | C24: Çengelköy Ofis Projesi | D24: 54000 | F24: 0.8 | G24: =IFERROR(D24*F24,"") -> 43200 | H24: Yes | I24: Unknown | J24: Yes | K24: Yes | L24: Yes | N24: inşai süreçte / mimari satın alma toplantısı olumlu | O24: =COUNTIF(H24:L24,"Yes")+COUNTIF(H24:L24,"No") -> 4
A25: BOFU | B25: İrem | C25: Cup of Joy | D25: 42000 | F25: 0.9 | G25: =IFERROR(D25*F25,"") -> 37800 | H25: Yes | I25: Yes | J25: Yes | K25: Yes | L25: No | N25: onaylandı ödeme gelicek | O25: =COUNTIF(H25:L25,"Yes")+COUNTIF(H25:L25,"No") -> 5
A26: BOFU | B26: Burçin | C26: Kundu Voyage - ek | D26: 33000 | E26: 2026-03-05 00:00:00 | F26: 1 | G26: =IFERROR(D26*F26,"") -> 33000 | H26: Yes | I26: Yes | J26: Yes | K26: Yes | L26: No | N26: onaylandı, sipariş girildi. ödeme bekleniyor | O26: =COUNTIF(H26:L26,"Yes")+COUNTIF(H26:L26,"No") -> 5
A27: BOFU | B27: Elif | C27: Tapestry Gümüşsuyu Hilton | D27: 88437 | F27: 0.25 | G27: =IFERROR(D27*F27,"") -> 22109.25 | H27: Yes | I27: Yes | J27: No | K27: Yes | L27: Unknown | N27: 09.04.2026 mail attım | O27: =COUNTIF(H27:L27,"Yes")+COUNTIF(H27:L27,"No") -> 4
A28: BOFU | B28: İrem | C28: Aydın Kuruyemiş | D28: 430000 | F28: 0.05 | G28: =IFERROR(D28*F28,"") -> 21500 | H28: Yes | I28: No | J28: No | K28: Yes | L28: Yes | N28: 12/2025 de çalışıldı, hala karar aşamasında | O28: =COUNTIF(H28:L28,"Yes")+COUNTIF(H28:L28,"No") -> 5
A29: BOFU | B29: İrem | C29: HSBC | D29: 35000 | F29: 0.6 | G29: =IFERROR(D29*F29,"") -> 21000 | H29: Yes | I29: No | J29: No | K29: Yes | L29: Yes | N29: bütçe onayından geçmesi bekleniyor | O29: =COUNTIF(H29:L29,"Yes")+COUNTIF(H29:L29,"No") -> 5
A30: BOFU | B30: İrem | C30: Caudile Kanyon | D30: 29000 | F30: 0.6 | G30: =IFERROR(D30*F30,"") -> 17400 | H30: Yes | I30: Yes | J30: Yes | K30: Yes | L30: No | O30: =COUNTIF(H30:L30,"Yes")+COUNTIF(H30:L30,"No") -> 5
A31: BOFU | B31: İrem | C31: Bodrum Bodrum | D31: 238000 | E31: ? | F31: 0.05 | G31: =IFERROR(D31*F31,"") -> 11900 | H31: Yes | I31: No | J31: Unknown | K31: Yes | L31: Yes | N31: reminded, geri dönüşe bağlı ilerlenecek | O31: =COUNTIF(H31:L31,"Yes")+COUNTIF(H31:L31,"No") -> 4
A32: BOFU | B32: Burçin | C32: Barut Anda Otel | D32: 11000 | E32: 2026-03-14 00:00:00 | F32: 1 | G32: =IFERROR(D32*F32,"") -> 11000 | H32: Yes | I32: Yes | J32: Yes | K32: Yes | L32: No | N32: onaylandı sipariş girildi . ödeme bekleniyor | O32: =COUNTIF(H32:L32,"Yes")+COUNTIF(H32:L32,"No") -> 5
A33: BOFU | B33: Burçin | C33: Circle Bodrum | D33: 11250 | E33: 2026-05-01 00:00:00 | F33: 0.85 | G33: =IFERROR(D33*F33,"") -> 9562.5 | H33: Yes | I33: Yes | J33: Yes | K33: Yes | L33: No | N33: onay bekleniyor | O33: =COUNTIF(H33:L33,"Yes")+COUNTIF(H33:L33,"No") -> 5
A34: BOFU | B34: İrem | C34: TimeValee PopUp | D34: 10000 | F34: 0.6 | G34: =IFERROR(D34*F34,"") -> 6000 | H34: Yes | I34: Yes | J34: Yes | K34: Yes | L34: Yes | N34: yeni teklif verildi / önceden çalıştığımız bir müşteri | O34: =COUNTIF(H34:L34,"Yes")+COUNTIF(H34:L34,"No") -> 5
A35: MOFU | B35: Zeynep | C35: daax walter knoll paket | D35: 665000 | F35: 0.8 | G35: =IFERROR(D35*F35,"") -> 532000 | H35: No | I35: Yes | J35: Yes | K35: Yes | L35: No | M35: ZAHA HADİD | N35: HAZIRLIK | O35: =COUNTIF(H35:L35,"Yes")+COUNTIF(H35:L35,"No") -> 5
A36: MOFU | B36: İrem | C36: kadoil yonetim kat | D36: 572000 | F36: 0.55 | G36: =IFERROR(D36*F36,"") -> 314600 | H36: Unknown | I36: Yes | J36: No | K36: Yes | L36: Unknown | N36: 11/2025 de çalışıldı, henüz karar verilmemiş. | O36: =COUNTIF(H36:L36,"Yes")+COUNTIF(H36:L36,"No") -> 3
A37: MOFU | B37: Burçin | C37: Divan Göcek | D37: 341280 | E37: 2026-11-15 00:00:00 | F37: 0.55 | G37: =IFERROR(D37*F37,"") -> 187704 | H37: Yes | I37: Yes | J37: Unknown | K37: Yes | L37: Unknown | M37: Metex Sinan Kafadar | N37: yatırımcı ile görüşüldü , mock up için bütçe üzeri kaldık. Genel paket için ayrıca çalışacağız Mimar Sinan Kafadar. Satınalım tahmini kasım 2026 , açılış 2027 başı . | O37: =COUNTIF(H37:L37,"Yes")+COUNTIF(H37:L37,"No") -> 3
A38: MOFU | B38: Zeynep | C38: THY JFK | D38: 299000 | E38: end of april | F38: 0.6 | G38: =IFERROR(D38*F38,"") -> 179400 | H38: Yes | I38: Yes | J38: No | K38: Yes | L38: Yes | M38: INHOUSE+AUTOBAN | N38: İLK TEKLİF | O38: =COUNTIF(H38:L38,"Yes")+COUNTIF(H38:L38,"No") -> 5
A39: MOFU | B39: İrem | C39: AAW-Maslak Ofis | D39: 196000 | E39: inşaat aşamasında | F39: 0.6 | G39: =IFERROR(D39*F39,"") -> 117600 | H39: Yes | I39: Yes | J39: No | K39: Yes | L39: No | O39: =COUNTIF(H39:L39,"Yes")+COUNTIF(H39:L39,"No") -> 5
A40: MOFU | B40: Burçin | C40: DIVAN AKARETLER SUIT | D40: 100000 | E40: 2026-06-30 00:00:00 | F40: 0.99 | G40: =IFERROR(D40*F40,"") -> 99000 | H40: Unknown | I40: Yes | J40: Yes | K40: Yes | L40: Unknown | M40: Tabanlıoğlu Mim | N40: Tabanalıoglundan son adetler bekleniyor. Haziran sonu teslim ! | O40: =COUNTIF(H40:L40,"Yes")+COUNTIF(H40:L40,"No") -> 3
A41: MOFU | B41: Zeynep | C41: thy kahire | D41: 189000 | F41: 0.5 | G41: =IFERROR(D41*F41,"") -> 94500 | H41: Yes | I41: Yes | J41: No | K41: Yes | L41: Yes | M41: INHOUSE+AUTOBAN | O41: =COUNTIF(H41:L41,"Yes")+COUNTIF(H41:L41,"No") -> 5
A42: MOFU | B42: İrem | C42: Emlak Katılım | D42: 90000 | E42: soon | F42: 0.45 | G42: =IFERROR(D42*F42,"") -> 40500 | H42: Yes | I42: No | J42: No | K42: Yes | L42: Unknown | N42: teklif verildi & reminded , dönüş bekleniyor | O42: =COUNTIF(H42:L42,"Yes")+COUNTIF(H42:L42,"No") -> 4
A43: MOFU | B43: Zeynep | C43: ıga genel havacılık terminalı | D43: 92000 | E43: NEXT WEEK | F43: 0.4 | G43: =IFERROR(D43*F43,"") -> 36800 | H43: Yes | I43: Yes | J43: Yes | K43: Yes | L43: Yes | M43: INHOUSE+AUTOBAN | N43: STOK URUN OLDUGU İÇİN KONU ACİL | O43: =COUNTIF(H43:L43,"Yes")+COUNTIF(H43:L43,"No") -> 5
A44: MOFU | B44: Burçin | C44: OZ RESTAURANT | D44: 75000 | E44: belirsiz | F44: 0.49 | G44: =IFERROR(D44*F44,"") -> 36750 | H44: Yes | I44: Yes | J44: No | K44: Yes | L44: Unknown | M44: Misa mimarlık | N44: alternatif ürünler için fiyat toplanıyori açılış + bütçe belirsiz. | O44: =COUNTIF(H44:L44,"Yes")+COUNTIF(H44:L44,"No") -> 4
A45: MOFU | B45: Elif | C45: Medipol Kavacık Yurt | D45: 720000 | F45: 0.05 | G45: =IFERROR(D45*F45,"") -> 36000 | H45: Yes | I45: No | J45: No | K45: No | L45: Yes | M45: Yapı Artı | N45: ihale dosyası gönderildi | O45: =COUNTIF(H45:L45,"Yes")+COUNTIF(H45:L45,"No") -> 5
A46: MOFU | B46: Elif | C46: SEHER AYDINLAR OFİS | D46: 60000 | E46: 2026 | F46: 0.45 | G46: =IFERROR(D46*F46,"") -> 27000 | H46: No | I46: Yes | J46: No | K46: Yes | L46: No | M46: Norm Mimarlık | N46: Vural Bey'i aradım yarın dönüş yapacak 08.04.2026 | O46: =COUNTIF(H46:L46,"Yes")+COUNTIF(H46:L46,"No") -> 5
A47: MOFU | B47: Burçin | C47: BEEFBAR ORTAKÖY | D47: 25000 | E47: 2026-08-01 00:00:00 | F47: 0.95 | G47: =IFERROR(D47*F47,"") -> 23750 | H47: No | I47: Yes | J47: Yes | K47: Unknown | L47: No | M47: Geo_id | N47: açılış 2026 Eylül e ertelendi , paketi bekletiyorlar.Geo_id ile görüşülüyor. ürünler özel üreim | O47: =COUNTIF(H47:L47,"Yes")+COUNTIF(H47:L47,"No") -> 4
A48: MOFU | B48: Zeynep | C48: çalık yonetici odası | D48: 56000 | F48: 0.4 | G48: =IFERROR(D48*F48,"") -> 22400 | H48: Yes | I48: Yes | J48: No | K48: Yes | L48: No | M48: INHOUSE | N48: teklif verildi | O48: =COUNTIF(H48:L48,"Yes")+COUNTIF(H48:L48,"No") -> 5
A49: MOFU | B49: Burçin | C49: JW Marriott Ankara | D49: 70000 | E49: 2026-04-20 00:00:00 | F49: 0.25 | G49: =IFERROR(D49*F49,"") -> 17500 | H49: Unknown | I49: Yes | J49: Unknown | K49: Unknown | L49: Yes | M49: evet | N49: Otel geneli için showroom görselleri ve referanslar mimar & ilgili kişi ve yatırımcıya gönderildi İstanbul daveti yapıldı | O49: =COUNTIF(H49:L49,"Yes")+COUNTIF(H49:L49,"No") -> 2
A50: MOFU | B50: İrem | C50: Doğuhan Emiruras Tekne ( doğan holding ) | D50: 27000 | F50: 0.6 | G50: =IFERROR(D50*F50,"") -> 16200 | H50: Yes | I50: No | J50: No | K50: Yes | L50: Yes | N50: teklif verildi, mşteriden dönüş bekleniyor | O50: =COUNTIF(H50:L50,"Yes")+COUNTIF(H50:L50,"No") -> 5
A51: MOFU | B51: Burçin | C51: The Marmara Bodrum | D51: 18000 | E51: 2026-05-01 00:00:00 | F51: 0.85 | G51: =IFERROR(D51*F51,"") -> 15300 | H51: Yes | I51: Yes | J51: Yes | K51: Unknown | L51: Unknown | M51: Cengiz Kurt | N51: teklif büyüyor alternatif ürünler önerildi | O51: =COUNTIF(H51:L51,"Yes")+COUNTIF(H51:L51,"No") -> 3
A52: MOFU | B52: Elif | C52: Mensis Energy | D52: 258000 | E52: 2026 haziran | F52: 0.05 | G52: =IFERROR(D52*F52,"") -> 12900 | H52: Unknown | I52: Yes | J52: Yes | K52: Unknown | L52: No | M52: evet | N52: 14.04.2026 norm ile görüşüldü yarın toplantıları var. | O52: =COUNTIF(H52:L52,"Yes")+COUNTIF(H52:L52,"No") -> 3
A53: MOFU | B53: İrem | C53: Sneaks-Up | D53: 26000 | F53: 0.25 | G53: =IFERROR(D53*F53,"") -> 6500 | H53: Yes | I53: No | J53: Yes | K53: Yes | L53: Yes | N53: reminded,geri dönüş olmadı | O53: =COUNTIF(H53:L53,"Yes")+COUNTIF(H53:L53,"No") -> 5
A54: MOFU | B54: İrem | C54: EFS ÇELİKTAŞ OFİS | D54: 10000 | F54: 0.6 | G54: =IFERROR(D54*F54,"") -> 6000 | H54: Yes | I54: Yes | J54: Unknown | K54: Yes | L54: No | N54: efs / alternatifli teklif verildi | O54: =COUNTIF(H54:L54,"Yes")+COUNTIF(H54:L54,"No") -> 4
A55: MOFU | B55: Burçin | C55: Sardunya Selimiye Otel | D55: 17000 | E55: 46127 | F55: 0.2 | G55: =IFERROR(D55*F55,"") -> 3400 | H55: Unknown | I55: Yes | J55: Yes | K55: Yes | L55: Yes | M55: hayır | O55: =COUNTIF(H55:L55,"Yes")+COUNTIF(H55:L55,"No") -> 4
A56: MOFU | B56: İrem | C56: Projeckt Hous | D56: 30000 | F56: 0.05 | G56: =IFERROR(D56*F56,"") -> 1500 | H56: Yes | I56: Yes | J56: No | K56: No | L56: Unknown | N56: bütçe toplantısından geçmeli | O56: =COUNTIF(H56:L56,"Yes")+COUNTIF(H56:L56,"No") -> 4
A57: MOFU | B57: İrem | C57: Riyadh CEO Office | D57: 75000 | F57: 0.01 | G57: =IFERROR(D57*F57,"") -> 750 | H57: Yes | I57: Yes | J57: No | K57: No | L57: Yes | N57: showroom ziyaretine gelicekler(miş) | O57: =COUNTIF(H57:L57,"Yes")+COUNTIF(H57:L57,"No") -> 5
A58: MOFU | B58: İrem | C58: KAYA ERSU OFİS | D58: 33000 | G58: =IFERROR(D58*F58,"") -> 0 | H58: Unknown | I58: Unknown | J58: Unknown | K58: Unknown | L58: Unknown | N58: seçilen ürünlere teklif verildi | O58: =COUNTIF(H58:L58,"Yes")+COUNTIF(H58:L58,"No") -> 0
A59: MOFU | B59: İrem | C59: ENSAR TEKSTİL | D59: 19000 | G59: =IFERROR(D59*F59,"") -> 0 | H59: Yes | I59: No | J59: Unknown | K59: Unknown | L59: Unknown | N59: seçilen ürünlere teklif verildi | O59: =COUNTIF(H59:L59,"Yes")+COUNTIF(H59:L59,"No") -> 2
A60: MOFU | B60: Burçin | C60: İstinyepark food court | F60: 0.51 | G60: =IFERROR(D60*F60,"") -> 0 | H60: Yes | I60: Unknown | J60: Unknown | K60: Yes | L60: Unknown | M60: Orjin Grup | O60: =COUNTIF(H60:L60,"Yes")+COUNTIF(H60:L60,"No") -> 2
A61: MOFU | B61: Elif | C61: CENGİZ ANTALYA OTEL | G61: =IFERROR(D61*F61,"") -> 0 | H61: No | I61: Yes | J61: Unknown | K61: Unknown | L61: Unknown | M61: Atıldan Ozel Bar Studio | N61: 2026 aralık MİMAR BARSTUDIO / Nisan 7 - 8 mimarlar ve yatırımcının şantiyede toplantısı olacak.Mimar netleşirse prpje başlayacak , şansımız çok yüksek !!!! | O61: =COUNTIF(H61:L61,"Yes")+COUNTIF(H61:L61,"No") -> 2
A62: MOFU | B62: İrem | C62: Özdilek TOSAB Fabrika | F62: 0.01 | G62: =IFERROR(D62*F62,"") -> 0 | H62: Yes | I62: Yes | J62: Yes | K62: Yes | L62: Yes | O62: =COUNTIF(H62:L62,"Yes")+COUNTIF(H62:L62,"No") -> 5
A63: MOFU | B63: İrem | C63: ESAS HOLDİNG YÖNETİM KATI | F63: 0.4 | G63: =IFERROR(D63*F63,"") -> 0 | H63: No | I63: Yes | J63: Yes | K63: Yes | L63: Yes | N63: fourandmore ile takipteyiz | O63: =COUNTIF(H63:L63,"Yes")+COUNTIF(H63:L63,"No") -> 5
A64: MOFU | B64: İrem | C64: HAS&KOEN FAB PROJECT | F64: 0.51 | G64: =IFERROR(D64*F64,"") -> 0 | H64: Unknown | I64: Yes | J64: Unknown | K64: Unknown | L64: Unknown | N64: seçilen ürünlere teklif verildi | O64: =COUNTIF(H64:L64,"Yes")+COUNTIF(H64:L64,"No") -> 1
A65: TOFU | B65: Zeynep | C65: polat psm projesi | D65: 1159000 | E65: 2026-05-11 00:00:00 | F65: 0.2 | G65: =IFERROR(D65*F65,"") -> 231800 | H65: Yes | I65: Yes | J65: No | K65: Yes | L65: Yes | M65: inhouse | N65: teklif yollandı teknik spect markadan bekliyoruz | O65: =COUNTIF(H65:L65,"Yes")+COUNTIF(H65:L65,"No") -> 5
A66: TOFU | B66: Zeynep | C66: KUVEYTTURK EK KATLAR | D66: 0 | F66: 0.95 | G66: =IFERROR(D66*F66,"") -> 0 | H66: No | I66: Yes | J66: No | K66: Yes | L66: Yes | M66: KREATIF | N66: TAKİP | O66: =COUNTIF(H66:L66,"Yes")+COUNTIF(H66:L66,"No") -> 5
A67: TOFU | B67: Zeynep | C67: TERA BANK | D67: 0 | F67: 0.8 | G67: =IFERROR(D67*F67,"") -> 0 | H67: No | I67: Yes | J67: No | K67: No | L67: Yes | M67: TEAM PROJECT | N67: SUNUM HAZırlandı mimardan TOPLANTI RİCA EDİLDİ | O67: =COUNTIF(H67:L67,"Yes")+COUNTIF(H67:L67,"No") -> 5
A68: TOFU | B68: Zeynep | C68: CERIST | D68: 0 | F68: 0.8 | G68: =IFERROR(D68*F68,"") -> 0 | H68: No | I68: Yes | J68: No | K68: Yes | L68: Yes | M68: HAN TUMERTEKIN | N68: SUNUM HAZIRLANACAK | O68: =COUNTIF(H68:L68,"Yes")+COUNTIF(H68:L68,"No") -> 5
A69: TOFU | B69: Zeynep | C69: işbank yonetim katları | F69: 0.85 | G69: =IFERROR(D69*F69,"") -> 0 | H69: No | I69: No | J69: No | K69: Yes | L69: No | N69: ihale process | O69: =COUNTIF(H69:L69,"Yes")+COUNTIF(H69:L69,"No") -> 5
A70: TOFU | B70: Zeynep | C70: Garanti – Çalışma Sandalye | F70: 0.5 | G70: =IFERROR(D70*F70,"") -> 0 | H70: Yes | I70: Yes | J70: Yes | K70: Yes | L70: Yes | N70: musteriden bu satınalımı yapıp yapmayacagını bekliyoruz. DEĞİŞİM DAHA YUKSEK | O70: =COUNTIF(H70:L70,"Yes")+COUNTIF(H70:L70,"No") -> 5
A71: TOFU | B71: Zeynep | C71: p&g framery | G71: =IFERROR(D71*F71,"") -> 0 | H71: No | I71: No | J71: No | K71: No | L71: No | N71: lead | O71: =COUNTIF(H71:L71,"Yes")+COUNTIF(H71:L71,"No") -> 5
A72: TOFU | B72: Zeynep | C72: beymen ifm | E72: 2026-05-15 00:00:00 | F72: 0.9 | G72: =IFERROR(D72*F72,"") -> 0 | H72: No | I72: Yes | J72: Yes | K72: Yes | L72: No | M72: bağımsız mimarlar +beymen inhouse | N72: SUNUM YAPILDI. eylul acılıs | O72: =COUNTIF(H72:L72,"Yes")+COUNTIF(H72:L72,"No") -> 5
A73: TOFU | B73: Zeynep | C73: beymen zorlu | E73: 2026-12-12 00:00:00 | F73: 0.9 | G73: =IFERROR(D73*F73,"") -> 0 | H73: No | I73: Yes | J73: Yes | K73: Yes | L73: No | M73: yabu pushenberg | N73: 2027 | O73: =COUNTIF(H73:L73,"Yes")+COUNTIF(H73:L73,"No") -> 5
A74: TOFU | B74: Zeynep | C74: beymen armada | E74: 2026-12-12 00:00:00 | F74: 0.9 | G74: =IFERROR(D74*F74,"") -> 0 | H74: No | I74: Yes | J74: Yes | K74: Yes | L74: No | N74: 2027 | O74: =COUNTIF(H74:L74,"Yes")+COUNTIF(H74:L74,"No") -> 5
A75: TOFU | B75: Zeynep | C75: denizbank sosyal alan | E75: 2026-05-11 00:00:00 | G75: =IFERROR(D75*F75,"") -> 0 | H75: No | I75: Yes | J75: No | K75: No | L75: Yes | M75: jeyabn ulku arc | N75: sunum hazırlanıyor | O75: =COUNTIF(H75:L75,"Yes")+COUNTIF(H75:L75,"No") -> 5
A76: TOFU | B76: Zeynep | C76: Four season satış ofisi+penthouse | E76: 2026-05-11 00:00:00 | F76: 0.5 | G76: =IFERROR(D76*F76,"") -> 0 | H76: No | I76: Yes | J76: No | K76: Yes | L76: Yes | M76: sinan kafadar | N76: sunum yapılıyor musteriye top musteride | O76: =COUNTIF(H76:L76,"Yes")+COUNTIF(H76:L76,"No") -> 5
A77: TOFU | B77: Zeynep | C77: bilişim ofisi projesi faz 0 | E77: 2026-05-11 00:00:00 | F77: 0.4 | G77: =IFERROR(D77*F77,"") -> 0 | H77: Yes | I77: Yes | J77: No | K77: Yes | L77: Yes | M77: norm | N77: teklif yollandı | O77: =COUNTIF(H77:L77,"Yes")+COUNTIF(H77:L77,"No") -> 5
A78: TOFU | B78: Burçin | C78: AMANRUYA | D78: 0 | G78: =IFERROR(D78*F78,"") -> 0 | H78: No | I78: Unknown | J78: Unknown | K78: Unknown | L78: Unknown | M78: Atılgan özel VE ?? | N78: Atılgan Özel ile örnek villalar yapıalcak , takip ediyoruz. Otel bölümü için daha zaman var | O78: =COUNTIF(H78:L78,"Yes")+COUNTIF(H78:L78,"No") -> 1
A79: TOFU | B79: Burçin | C79: Bulgari Bodrum SatışOFİS | G79: =IFERROR(D79*F79,"") -> 0 | H79: Unknown | I79: Yes | J79: Unknown | K79: Unknown | L79: Unknown | M79: ZD Group | N79: Haziran ilk hafta satış ofisi açılışı hedefleniyor, çok kısıtlı süre. önümüzdeki hafta 14.04 malzeme seçimleri yapılacak. yatırımcıdan teklif isteği bekleniyor - Cengiz Holding | O79: =COUNTIF(H79:L79,"Yes")+COUNTIF(H79:L79,"No") -> 1
A80: TOFU | B80: Burçin | C80: MAXX ROYAL MALDIVLER | G80: =IFERROR(D80*F80,"") -> 0 | H80: No | I80: Unknown | J80: Unknown | K80: Unknown | L80: Unknown | M80: Autoban | N80: 2026 aralık sezon açılış. Paket bekleniyor. yatırımcı + ceo ile süreli irtibattayız. Mimar bizi sevmiyor ancak Maxx Royal grup proje partneriyiz | O80: =COUNTIF(H80:L80,"Yes")+COUNTIF(H80:L80,"No") -> 1
A81: TOFU | B81: Burçin | C81: MAXX ROYAL BELEK | E81: 2027 Sezon | F81: 0.99 | G81: =IFERROR(D81*F81,"") -> 0 | H81: Unknown | I81: Unknown | J81: Unknown | K81: Unknown | L81: Unknown | M81: ??? | N81: Maxx Royal grup proje partneriyiz şansımız yüksek, mevcut otel renovasyona girecek. HBA Sayeli uysal ile görüşülecek . HBA İptal Arketipo ile görüşülüyor | O81: =COUNTIF(H81:L81,"Yes")+COUNTIF(H81:L81,"No") -> 0
A82: TOFU | B82: Burçin | C82: Ankara Savunma sanayi | G82: =IFERROR(D82*F82,"") -> 0 | H82: Unknown | I82: Unknown | J82: Unknown | K82: Unknown | L82: Unknown | N82: 84 adet 4 haftada teslim sandalye için çalışıyoruz. | O82: =COUNTIF(H82:L82,"Yes")+COUNTIF(H82:L82,"No") -> 0
A83: TOFU | B83: Burçin | C83: SİRKECİ GAR OTEL | G83: =IFERROR(D83*F83,"") -> 0 | H83: Unknown | I83: Unknown | J83: Unknown | K83: Unknown | L83: Unknown | M83: Gökcan Bulut | N83: mimar ile görüşüldü yeni otel projesi , bekliyoruz..TOSMUR Group | O83: =COUNTIF(H83:L83,"Yes")+COUNTIF(H83:L83,"No") -> 0
A84: TOFU | B84: Burçin | C84: FİKO POLİGON | G84: =IFERROR(D84*F84,"") -> 0 | H84: No | I84: Unknown | J84: Yes | K84: Unknown | L84: Unknown | M84: Misa mimarlık | N84: Önerile uygun bulunmadı , yeni öneri yapılacak düşük bütçe | O84: =COUNTIF(H84:L84,"Yes")+COUNTIF(H84:L84,"No") -> 2
A85: TOFU | B85: Burçin | C85: ST REGIS KARYA COVE RESORT BODRUM | E85: 2027 Haziran | G85: =IFERROR(D85*F85,"") -> 0 | H85: Unknown | I85: Unknown | J85: Unknown | K85: Unknown | L85: Unknown | M85: ÖĞREN ??? | N85: Access hospitality Haluk Özdoğan ile 27. 04 görüşülecek . Yatırımcı Kuzu Grıup | O85: =COUNTIF(H85:L85,"Yes")+COUNTIF(H85:L85,"No") -> 0
A86: TOFU | B86: Burçin | C86: THY OTEL | D86: 0 | G86: =IFERROR(D86*F86,"") -> 0 | H86: No | I86: Unknown | J86: Unknown | K86: Unknown | L86: Unknown | M86: Sevimlisoy Mim. | N86: işletmeci grup Grand Yazıcı ile sürekli iletişime geçmeye çalışılıyor, cevap yok . şantiye ? | O86: =COUNTIF(H86:L86,"Yes")+COUNTIF(H86:L86,"No") -> 1
A87: TOFU | B87: Burçin | C87: grand tarabya - accor fairmont oluyor ! | D87: 0 | G87: =IFERROR(D87*F87,"") -> 0 | H87: No | I87: Unknown | J87: Unknown | K87: Unknown | L87: Unknown | M87: Yeşim Kozanlı | N87: Marka değişiyor , otel komple renovasyona girecek. | O87: =COUNTIF(H87:L87,"Yes")+COUNTIF(H87:L87,"No") -> 1
A88: TOFU | B88: Burçin | C88: Hyatt Regency Ataköy Rams a satılmış ! | G88: =IFERROR(D88*F88,"") -> 0 | H88: Unknown | I88: Unknown | J88: Unknown | K88: Unknown | L88: Unknown | O88: =COUNTIF(H88:L88,"Yes")+COUNTIF(H88:L88,"No") -> 0
A89: TOFU | B89: Burçin | C89: LUJO KERPİC | D89: 0 | G89: =IFERROR(D89*F89,"") -> 0 | H89: No | I89: Unknown | J89: Unknown | K89: Unknown | L89: Unknown | M89: ? | N89: otelin sahibi ile görüşüldü, miamr belli değil proje başında dahil olmak için sıkı takip ! | O89: =COUNTIF(H89:L89,"Yes")+COUNTIF(H89:L89,"No") -> 1
A90: TOFU | B90: Burçin | C90: GRAND HYATT TAKSİM - DOĞUŞ | D90: 0 | G90: =IFERROR(D90*F90,"") -> 0 | H90: No | I90: Unknown | J90: Unknown | K90: Unknown | L90: Unknown | M90: ? | N90: Renovasyona gireceğini öğrendik, Doğuş Hospitality ile iletişime geçeceğiz | O90: =COUNTIF(H90:L90,"Yes")+COUNTIF(H90:L90,"No") -> 1
A91: TOFU | B91: Burçin | C91: BEACH PROJE I AM IST | D91: 0 | G91: =IFERROR(D91*F91,"") -> 0 | H91: No | I91: Unknown | J91: Unknown | K91: Unknown | L91: Unknown | M91: I AM ISTANBUL | N91: Mimara örnek sunumlar & alt. ürünler gönderildi . gelişme olmadı | O91: =COUNTIF(H91:L91,"Yes")+COUNTIF(H91:L91,"No") -> 1
A92: TOFU | B92: Burçin | C92: FIKO YALIKAVAK | D92: 0 | G92: =IFERROR(D92*F92,"") -> 0 | H92: No | I92: Unknown | J92: Unknown | K92: Unknown | L92: Unknown | M92: Misa mimarlık | N92: yatırımcı ile görüşüldü, mevcut restoranın sandalyeleri değişecek , takip ! | O92: =COUNTIF(H92:L92,"Yes")+COUNTIF(H92:L92,"No") -> 1
A93: TOFU | B93: Burçin | C93: SHANGRIA YALIKAVAK | D93: 0 | G93: =IFERROR(D93*F93,"") -> 0 | H93: No | I93: Unknown | J93: Unknown | K93: Unknown | L93: Unknown | M93: ???? | N93: 2029 açılış - mimar kim ? araştır | O93: =COUNTIF(H93:L93,"Yes")+COUNTIF(H93:L93,"No") -> 1
A94: TOFU | B94: Burçin | C94: KIZILAGAÇ YALIÇIFTLIK OTEL KALYON | E94: 2029 | G94: =IFERROR(D94*F94,"") -> 0 | H94: Unknown | I94: Unknown | J94: Unknown | K94: Unknown | L94: Unknown | M94: AW2 ARCH. | N94: AW2 ARCH. DOME+PARTNERS ? İNTERİOR ? | O94: =COUNTIF(H94:L94,"Yes")+COUNTIF(H94:L94,"No") -> 0
A95: TOFU | B95: Burçin | C95: LONDRA OTEL | G95: =IFERROR(D95*F95,"") -> 0 | H95: Unknown | I95: Unknown | J95: Unknown | K95: Unknown | L95: Unknown | O95: =COUNTIF(H95:L95,"Yes")+COUNTIF(H95:L95,"No") -> 0
A96: TOFU | B96: Burçin | C96: ION RIVA OTEL & KONUT & SOSYAL ALANLAR | E96: 2027 | G96: =IFERROR(D96*F96,"") -> 0 | H96: Unknown | I96: Unknown | J96: Unknown | K96: Unknown | L96: Unknown | N96: yatırımcı ile görüşüldü. Konut & otel & sosyal alanlar çok kapsamlı proje. mimar : snohetta /big /bilgin studio/ | O96: =COUNTIF(H96:L96,"Yes")+COUNTIF(H96:L96,"No") -> 0
A97: TOFU | B97: Elif | C97: MEDİPOL | D97: 0 | F97: 0.05 | G97: =IFERROR(D97*F97,"") -> 0 | H97: No | I97: No | J97: Unknown | K97: Unknown | L97: Unknown | N97: Hasan beyden Rıza uçan numarasını aldım aradım açmadı tekrar | O97: =COUNTIF(H97:L97,"Yes")+COUNTIF(H97:L97,"No") -> 2
A98: TOFU | B98: Elif | C98: Swissotel Bosphorus | D98: 0 | E98: 2026 | G98: =IFERROR(D98*F98,"") -> 0 | H98: No | I98: Yes | J98: No | K98: No | L98: Unknown | M98: Designist | N98: iletişim bilgimi listelere eklediler | O98: =COUNTIF(H98:L98,"Yes")+COUNTIF(H98:L98,"No") -> 4
A99: TOFU | B99: Elif | C99: Acıbadem Hastahanesi Beylikdüzü | D99: 0 | E99: 2027 | G99: =IFERROR(D99*F99,"") -> 0 | H99: No | I99: Yes | J99: No | K99: No | L99: Yes | N99: Norm Mimarlık ile görüşüldü proje devam ediyor | O99: =COUNTIF(H99:L99,"Yes")+COUNTIF(H99:L99,"No") -> 5
A100: TOFU | B100: Elif | C100: Acıbadem Hastahanesi Ankara | D100: 0 | G100: =IFERROR(D100*F100,"") -> 0 | H100: No | I100: Yes | J100: No | K100: No | L100: Yes | O100: =COUNTIF(H100:L100,"Yes")+COUNTIF(H100:L100,"No") -> 5
...

Sheet Definitions
B2: Funnel Stage Definitions — tailored to Mozaik Design
B3: Mozaik's enterprise sales cycle involves an architect/specifier, a client/owner, and a product package (furniture, lighting, fabrics). Use the table below as the single source of truth for when a deal sits in each stage.
B6: Stage | C6: Entry criteria | D6: Exit criteria (move to next stage) | E6: Probability band
B7: TOFU (Top of Funnel) | C7: • Target company + contact identified • At least one meaningful touchpoint • Broad product fit plausible • No confirmed brief / budget / timeline yet | D7: • Specific project brief exists (name, location, scope) • Architect engaged OR RFP received • Indicative budget range known | E7: 10–25%
B8: MOFU (Middle of Funnel) | C8: • Project brief confirmed & quantified (€) • Architect actively specifying our products • Decision maker known and reachable • Proposal sent or scheduled | D8: • Proposal accepted verbally OR budget confirmed • Competitor set narrowed to us + 1, or sole source • Order/contract being drafted | E8: 30–70%
B9: BOFU (Bottom of Funnel) | C9: • Proposal sent AND approved • Budget explicitly confirmed • Decision maker committed • Compelling event exists (opening, season, move-in) | D9: • Signed order / contract received • Down-payment received OR corporate PO issued → Move to 'Won' | E9: 75–99%
B10: Won | C10: • PO / contract received • Down-payment received (if applicable) | D10: (terminal) | E10: 100%
B11: Lost | C11: • Competitor chose • Budget killed • Ghosted > 60 days • Timing slipped out of horizon | D11: (terminal — record lost reason) | E11: 0%
B13: Probability bands to standardize on
B14: Right now probabilities are free-form (0.01, 0.51, 0.97 etc.), which makes forecasting noisy. Use only these bands: TOFU → 10% / 20% · MOFU → 30% / 50% / 70% · BOFU → 80% / 90% / 100%. Any deal at 100% should be moved to a 'Won — awaiting PO/payment' stage, not left in BOFU.

Sheet Outbound
A1: Section | B1: Rep | C1: Company | D1: Contact | E1: Date | F1: Note
A2: HOSPITALITY | B2: Elif | C2: WANGAN
A3: HOSPITALITY | B3: Elif | C3: ÖZER+TULGAN
A4: HOSPITALITY | B4: Elif | C4: MURAT ÖZ
A5: HOSPITALITY | B5: Elif | C5: URBANJOBS
A6: HOSPITALITY | B6: Elif | C6: ZOOMTPU
A7: HOSPITALITY | B7: Elif | C7: KRN MIMARLIK
A8: HOSPITALITY | B8: Elif | C8: ACIBADEM PROJE YONETIM
A9: HOSPITALITY | B9: Elif | C9: DESIGNIST
A10: HOSPITALITY | B10: Elif | C10: SANAYI313
A11: HOSPITALITY | B11: Elif | C11: AYSE KUBILAY
A12: HOSPITALITY | B12: Elif | C12: SEÇİL ONUK | F12: ANKARA GÜVEN HASTANE
A13: HOSPITALITY | B13: Elif
A14: HOSPITALITY | B14: Elif
A15: HOSPITALITY | B15: Burçin | C15: NORM MIMARLIK | D15: EKIN PEKAKCAN | E15: 2026-04-15 00:00:00 | F15: Ekin Pekakcan Ve Esin Tersan ile görüşüldü. Beylikdüzü Acıbadem Proje ! Terminal Bilişim merkezi çok büyük proje olacak Zeynep çalışıyor. Salone sonrası yenilikler için görüşelim
A16: HOSPITALITY | B16: Burçin | C16: ACCESS HOSPITALITY | E16: 2026-04-15 00:00:00 | F16: 27.04 haftası Haluk Özdoğan ile görüşülecek
A17: HOSPITALITY | B17: Burçin | C17: GEO_ID | D17: TUĞÇE RİZELİ
A18: HOSPITALITY | B18: Burçin | C18: METEX | D18: SİNAN KAFADAR
A19: HOSPITALITY | B19: Burçin | C19: STUDIO ERK | D19: HÜRAY ERK
A20: HOSPITALITY | B20: Burçin | C20: SEVIMLI MIMARLIK
A21: HOSPITALITY | B21: Burçin | C21: TABANLIOĞLU
A22: HOSPITALITY | B22: Burçin | C22: MISA MIMARLIK | D22: AYŞE ÖZ
A23: HOSPITALITY | B23: Burçin | C23: KUD | D23: TOLGAN SENCER
A24: HOSPITALITY | B24: Burçin | C24: GULDEN ŞENER | D24: GULDEN ŞENER
A25: HOSPITALITY | B25: Burçin | C25: YEŞİM KOZANLI MIMARLIK | D25: BANU - KORAY KİDİŞ
A26: HOSPITALITY | B26: Burçin | C26: DOĞUŞ HOSPİTALITY | D26: RANA AKIN
A27: HOSPITALITY | B27: Burçin | C27: HILL INVESTMENT
A28: HOSPITALITY | B28: Burçin | C28: SERVOTEL | D28: ÖMER ISVAN
A29: OFIS | B29: İrem | C29: ALTIPATLAR ARCH. ** | D29: Yasin Altipat | F29: klinik projeler, colgate,Schwarzkopf Projesi
A30: OFIS | B30: İrem | C30: İKİBİNİKİ | D30: Adil Kırkaya (Ortak)-Erdem Argun (Ortak)
A31: OFIS | B31: İrem | C31: U DESIGN | D31: Umut Uzuner | F31: ofis, holding , "yeni ofis tasarımları"
A32: OFIS | B32: İrem | C32: DAM DESIGN | D32: Dicle DemirAlper TüzünoğluCo-Founder / Architects | F32: ofis,bank hq, hotel
A33: OFIS | B33: İrem | C33: DBS | D33: Muzaffer Emiroğlu kurucu ortak | F33: "dbs, bir Mimarlık ve mühendislik şirketidir. Kurumsal fit-out alanında ofis dizaynı ve uygulamaları yapar
A34: OFIS | B34: İrem | C34: ALYA ARCH.
A35: OFIS | B35: İrem | C35: GİZEM ŞİPKAN (MİMAR)
A36: OFIS | B36: İrem | C36: OSO ARCH.
A37: OFIS | B37: İrem | C37: OĞUL BURNAZ ARCH.
A38: OFIS | B38: Zeynep
A39: OFIS | B39: Zeynep
A40: OFIS | B40: Zeynep
A41: OFIS | B41: Zeynep

Sheet Data Quality
B2: Data Quality Audit — what's missing or inconsistent
B4: Field | C4: # Filled | D4: Fill % | E4: Comment
B5: Value (€) | C5: =COUNT(Opportunities!D2:D108) -> 75 | D5: =COUNT(Opportunities!D2:D108)/COUNTA(Opportunities!C2:C108) -> 0.70093458 | E5: 36 deals have text like 'teklif verildi' or are blank. Can't be summed or weighted.
B6: Close Date | C6: =COUNTA(Opportunities!E2:E108)-COUNTBLANK(Opportunities!E2:E108) -> -7 | D6: =COUNTA(Opportunities!E2:E108)/COUNTA(Opportunities!C2:C108) -> 0.46728972 | E6: Mix of real dates and free text ('soon', 'end of april', '2027'). Blocks time-phased forecast.
B7: Probability | C7: =COUNT(Opportunities!F2:F108) -> 79 | D7: =COUNT(Opportunities!F2:F108)/COUNTA(Opportunities!C2:C108) -> 0.73831776 | E7: Too many free values (0.01, 0.51, 0.97). Standardize to bands.
B8: Proposal Sent | C8: =COUNTIF(Opportunities!H2:H108,"Yes")+COUNTIF(Opportunities!H2:H108,"No") -> 88 | D8: =(COUNTIF(Opportunities!H2:H108,"Yes")+COUNTIF(Opportunities!H2:H108,"No"))/COUNTA(Opportunities!C2:C108) -> 0.82242991 | E8: Team is quoting before Budget is confirmed on many deals.
B9: Architect Engaged | C9: =COUNTIF(Opportunities!I2:I108,"Yes")+COUNTIF(Opportunities!I2:I108,"No") -> 83 | D9: =(COUNTIF(Opportunities!I2:I108,"Yes")+COUNTIF(Opportunities!I2:I108,"No"))/COUNTA(Opportunities!C2:C108) -> 0.77570093 | E9: Architect = strongest signal (85% Yes among filled). Double-down on outbound.
B10: Budget Confirmed | C10: =COUNTIF(Opportunities!J2:J108,"Yes")+COUNTIF(Opportunities!J2:J108,"No") -> 71 | D10: =(COUNTIF(Opportunities!J2:J108,"Yes")+COUNTIF(Opportunities!J2:J108,"No"))/COUNTA(Opportunities!C2:C108) -> 0.6635514 | E10: Biggest forecasting gap. Lowest fill rate of the five.
B11: Decision Maker Identified | C11: =COUNTIF(Opportunities!K2:K108,"Yes")+COUNTIF(Opportunities!K2:K108,"No") -> 75 | D11: =(COUNTIF(Opportunities!K2:K108,"Yes")+COUNTIF(Opportunities!K2:K108,"No"))/COUNTA(Opportunities!C2:C108) -> 0.70093458 | E11: Should be mandatory for MOFU+ entry.
B12: Competitor Present | C12: =COUNTIF(Opportunities!L2:L108,"Yes")+COUNTIF(Opportunities!L2:L108,"No") -> 68 | D12: =(COUNTIF(Opportunities!L2:L108,"Yes")+COUNTIF(Opportunities!L2:L108,"No"))/COUNTA(Opportunities!C2:C108) -> 0.63551402 | E12: Useful. Add specific competitor name field.
B13: Next Step | C13: =COUNTA(Opportunities!N2:N108)-COUNTBLANK(Opportunities!N2:N108) -> 83 | D13: =COUNTA(Opportunities!N2:N108)/COUNTA(Opportunities!C2:C108) -> 0.88785047 | E13: Exists as free text, but no owner and no due date.
B16: Structural gaps — fields that simply don't exist in the file
B17: • No Won / Lost stages → can't compute win rate or avg cycle time.
B18: • No stage-entered date → can't measure velocity or time-in-stage (Sales Velocity column exists but is 100% empty).
B19: • No lead source → can't tell which channel (architect referral / outbound / showroom / inbound) is converting.
B20: • No industry / vertical tag → can't compare Hospitality vs Office vs Yacht vs Retail vs Bank performance.
B21: • No Lost Reason drop-down → 'Ghosting / Operation / Time / Budget' only live in weekly notes.
B22: • No compelling event for MOFU/TOFU → field is only asked of BOFU today.
B23: • No Next Step owner / due date → no accountability on the weekly cadence.
B24: • No product / SKU / margin → can't forecast stock, GM% or category mix.
B25: • No contact name / role / email / phone → account record is incomplete.
B26: • Outbound sheet has no status or last-touch date → prospecting list is static, not working.

Sheet CRM Schema
B2: Recommended CRM schema (before migrating from this spreadsheet)
B3: Every field you need per opportunity for clean reporting. Required = must be filled to leave TOFU.
B5: Field | C5: Type | D5: Required | E5: Purpose / allowed values
B6: Account | C6: Text | D6: Yes | E6: Parent company (e.g. 'Doğuş Hospitality', 'Garanti BBVA')
B7: Project | C7: Text | D7: Yes | E7: Specific project name (e.g. 'Grand Tarabya – Fairmont')
B8: Owner / Rep | C8: Picklist | D8: Yes | E8: Burçin / Zeynep / İrem / Elif / Balamir
B9: Industry | C9: Picklist | D9: Yes | E9: Hospitality / Office / Yacht / Retail / Bank / Residential / Other
B10: Lead Source | C10: Picklist | D10: Yes | E10: Architect referral / Existing client / Outbound / Showroom / Inbound / Event
B11: Stage | C11: Picklist | D11: Yes | E11: TOFU / MOFU / BOFU / Won / Lost
B12: Stage-Entered Date | C12: Date | D12: Yes | E12: Auto-set when stage changes — drives velocity
B13: Value (€) | C13: Number | D13: MOFU+ | E13: Numeric EUR only; no text
B14: Close Date | C14: Date | D14: MOFU+ | E14: Realistic sign-date; must be a date, not 'soon'
B15: Probability | C15: Picklist | D15: Yes | E15: 10 / 20 / 30 / 50 / 70 / 80 / 90 / 100
B16: Compelling Event | C16: Text | D16: Yes | E16: Opening, season, move-in, lease end etc.
B17: Proposal Sent | C17: Yes/No | D17: Yes | E17: Standardize — replaces 'evet' / 'yes' / 'hayır' mix
B18: Architect Engaged | C18: Yes/No | D18: Yes
B19: Architect Firm | C19: Text | D19: Recommended | E19: Link to Architects table
B20: Budget Confirmed | C20: Yes/No | D20: Yes
B21: Decision Maker Name | C21: Text | D21: MOFU+ | E21: Plus role / email / phone
B22: Competitor | C22: Text | D22: Recommended | E22: Specific competitor, not just Yes/No
B23: Next Step | C23: Text | D23: Yes | E23: What is the single next action
B24: Next Step Owner | C24: Picklist | D24: Yes | E24: Rep / Architect / Client — who owns it
B25: Next Step Due | C25: Date | D25: Yes | E25: Drives the weekly cadence
B26: Last Activity Date | C26: Date | D26: Auto | E26: Auto-updated when any field changes
B27: Products / Category | C27: Multi-picklist | D27: MOFU+ | E27: Seating / Tables / Lighting / Fabrics / Accessories
B28: Expected Margin % | C28: Percent | D28: BOFU | E28: For GM forecasting
B29: Lost Reason | C29: Picklist | D29: If Lost | E29: Ghosting / Budget / Competitor / Timing / Operation / Price / Product mismatch
B30: Won Order Date | C30: Date | D30: If Won
