Workbook

Sheet Üst Yönetim Raporu
A1: LUXURY FURNITURE SALES METRICS - EXECUTIVE DASHBOARD
A3: COMPANY-WIDE METRICS | B3: Current Month | C3: Prior Month | D3: YoY % | E3: YTD Actual | F3: YTD Target | G3: Variance %
A4: Total Revenue ($) | B4: ='Satış Departman Verisi'!U3 -> 2820452.7 | C4: ='Satış Departman Verisi'!T3 -> 2539667.7 | D4: =(B4-C4)/C4 -> 0.11055974 | E4: =sum('Satış Departman Verisi'!M3:U3) -> 27588755 | F4: =sum('Satış Departmanı Verisi'!C3:N3) -> 32998728 | G4: =(E4-F4)/F4 -> -0.1639449
A5: Gross Margin (%)
A6: EBITDA ($)
A7: Customer Count
A8: Average Order Value ($)
A10: REVENUE BY DIVISION | B10: Current Month | C10: Prior Month | D10: YoY % | E10: Mix % | F10: YTD Actual | G10: YTD Target
A11: Retail Division | B11: ='Satış Departman Verisi'!U10 -> 1979165 | C11: ='Satış Departman Verisi'!T10 -> 1395066
A12: Enterprise Division | B12: ='Satış Departman Verisi'!U26 -> 313366 | C12: ='Satış Departman Verisi'!T26 -> 323951
A13: Lighting Division | B13: ='Satış Departman Verisi'!U42 -> 519257.15 | C13: ='Satış Departman Verisi'!T42 -> 813659.04
A14: Marketing Division
A15: Total Revenue | B15: =sum(B11:B14) -> 2811788.1 | C15: =sum(C11:C14) -> 2532676 | F15: 0
A17: KEY OPERATIONAL METRICS | B17: Current | C17: Target | D17: Status | E17: Trend
A18: Inventory Turnover (x) | D18: On Track
A19: Days Sales Outstanding | D19: On Track
A20: On-Time Delivery (%) | D20: On Track
A21: Customer Satisfaction (NPS) | D21: On Track
A22: Stock vs Custom Mix (%)

Sheet Satış Departman Verisi
C1: 2015 | D1: 2016 | E1: 2017 | F1: 2018 | G1: 2019 | H1: 2020 | I1: 2021 | J1: 2022 | K1: 2023 | L1: 2024 | M1: 45658 | N1: 45689 | O1: 45717 | P1: 45748 | Q1: 45778 | R1: 45809 | S1: 45839 | T1: 45870 | U1: 45901 | V1: 45931 | W1: 45962 | X1: 45992 | Y1: 46023 | Z1: 46024 | AA1: 46025
A3: Toplam Satış | C3: 13882589 | D3: 7111065 | E3: 10060317 | F3: 9817554 | G3: 8035913 | H3: 12854873 | I3: 11246016 | J3: 15938774 | K3: 19580773 | L3: 28260753 | M3: =M10+M26+M42+M56 -> 3408772.9 | N3: =N10+N26+N42+N56 -> 3091213.8 | O3: =O10+O26+O42+O56 -> 2306104.1 | P3: =P10+P26+P42+P56 -> 3474646.4 | Q3: =Q10+Q26+Q42+Q56 -> 2963094.5 | R3: =R10+R26+R42+R56 -> 2404086.7 | S3: =S10+S26+S42+S56 -> 4580716.2 | T3: =T10+T26+T42+T56 -> 2539667.7 | ... Z3: =Z10+Z26+Z42+Z56 -> 3677792.2
A4: Finance Team Report | M4: 1791751 | N4: 1619577 | O4: 3154045 | P4: 2387395 | Q4: 3066607 | R4: 2500075 | S4: 2189851 | T4: 2300554 | U4: 2522957 | V4: 2177152 | W4: 2289987 | X4: 2944065
A5: Muhasebe Departmanı | M5: =M4-M3 -> -1617021.9 | N5: =N4-N3 -> -1471636.8 | O5: =O4-O3 -> 847940.94 | P5: =P4-P3 -> -1087251.4 | Q5: =Q4-Q3 -> 103512.48 | R5: =R4-R3 -> 95988.264 | S5: =S4-S3 -> -2390865.2 | T5: =T4-T3 -> -239113.66 | ... X5: =X4-X3 -> -2783450.6 | AB5: 0.55
A6: Finans Departman | M6: 441524.9 | N6: 1057896.3 | O6: 17882 | P6: 619024 | Q6: 508500.85 | R6: 212456.9 | S6: 484393.07 | T6: 313595 | U6: 365933.65 | V6: 650581.5 | W6: 290183.55 | X6: 510225.55 | Y6: 2564702 | Z6: 1623071 | AB6: 4-8M TRY
A7: Difference | M7: =M3-M4-M6 -> 1175497 | N7: =N3-N4-N6 -> 413740.51 | O7: =O3-O4-O6 -> -865822.94 | P7: =P3-P4-P6 -> 468227.39 | Q7: =Q3-Q4-Q6 -> -612013.33 | R7: =R3-R4-R6 -> -308445.16 | S7: =S3-S4-S6 -> 1906472.1 | T7: =T3-T4-T6 -> -74481.338 | ... Z7: =Z3-Z4-Z6 -> 2054721.2
A8: Departman Performansı | B8: Mağaza(Retail)
B9: Satış Departmanı Kişi Sayısı | M9: 8 | N9: 8 | O9: 8 | P9: 8 | Q9: 7 | R9: 7 | S9: 7 | T9: 7 | U9: 7 | V9: 7 | W9: 7 | X9: 7 | Y9: 7 | Z9: 7
B10: Toplam Satış_Miktarı | M10: =sum(M69:M75) -> 1452181 | N10: =sum(N69:N75) -> 1508709 | O10: =sum(O69:O75) -> 1190281 | P10: =sum(P69:P75) -> 1868402 | Q10: =sum(Q69:Q75) -> 1807220 | R10: =sum(R69:R75) -> 1485332 | S10: =sum(S69:S75) -> 2203964 | T10: =sum(T69:T75) -> 1395066 | ... X10: =sum(X69:X75) -> 2068053 | Y10: =sum(Y69:Y77) -> 3179580 | Z10: =sum(Z69:Z77) -> 1790827 | AA10: 2500000
B11: Toplam Satış adeti | M11: =sum(M95:M101) -> 56 | N11: =sum(N95:N101) -> 63 | O11: =sum(O95:O101) -> 71 | P11: =sum(P95:P101) -> 67 | Q11: =sum(Q95:Q101) -> 122 | R11: =sum(R95:R101) -> 57 | S11: =sum(S95:S101) -> 89 | T11: =sum(T95:T101) -> 65 | ... Z11: =sum(Z95:Z101) -> 76
B12: Toplam Müşteri Sayısı | M12: =M236+M237+M239+M240+M242+M243+M245+M246+M248+M249+M251+M252+M254+M255 -> 54 | N12: =N236+N237+N239+N240+N242+N243+N245+N246+N248+N249+N251+N252+N254+N255 -> 50 | O12: =O236+O237+O239+O240+O242+O243+O245+O246+O248+O249+O251+O252+O254+O255 -> 69 | P12: =P236+P237+P239+P240+P242+P243+P245+P246+P248+P249+P251+P252+P254+P255 -> 49 | Q12: =Q236+Q237+Q239+Q240+Q242+Q243+Q245+Q246+Q248+Q249+Q251+Q252+Q254+Q255 -> 69 | R12: =R236+R237+R239+R240+R242+R243+R245+R246+R248+R249+R251+R252+R254+R255 -> 62 | S12: =S236+S237+S239+S240+S242+S243+S245+S246+S248+S249+S251+S252+S254+S255 -> 62 | T12: =T236+T237+T239+T240+T242+T243+T245+T246+T248+T249+T251+T252+T254+T255 -> 62 | ... Z12: =Z236+Z237+Z239+Z240+Z242+Z243+Z245+Z246+Z248+Z249+Z251+Z252+Z254+Z255 -> 48
B13: Toplam Yeni Müşteri Sayısı | M13: =M236+M239+M242+M245+M248+M251+M254 -> 30 | N13: =N236+N239+N242+N245+N248+N251+N254 -> 23 | O13: =O236+O239+O242+O245+O248+O251+O254 -> 32 | P13: =P236+P239+P242+P245+P248+P251+P254 -> 20 | Q13: =Q236+Q239+Q242+Q245+Q248+Q251+Q254 -> 33 | R13: =R236+R239+R242+R245+R248+R251+R254 -> 31 | S13: =S236+S239+S242+S245+S248+S251+S254 -> 32 | T13: =T236+T239+T242+T245+T248+T251+T254 -> 31 | ... Z13: =Z236+Z239+Z242+Z245+Z248+Z251+Z254 -> 15
B14: Yeni Müşteri Oranı | M14: =M13/M12 -> 0.55555556 | N14: =N13/N12 -> 0.46 | O14: =O13/O12 -> 0.46376812 | P14: =P13/P12 -> 0.40816327 | Q14: =Q13/Q12 -> 0.47826087 | R14: =R13/R12 -> 0.5 | S14: =S13/S12 -> 0.51612903 | T14: =T13/T12 -> 0.5 | ... Z14: =Z13/Z12 -> 0.3125
B15: Ortalama Sepet Değeri | M15: =M10/M9 -> 181522.62 | N15: =N10/N9 -> 188588.62 | O15: =O10/O9 -> 148785.12 | P15: =P10/P9 -> 233550.25 | Q15: =Q10/Q9 -> 258174.29 | R15: =R10/R9 -> 212190.29 | S15: =S10/S9 -> 314852 | T15: =T10/T9 -> 199295.14 | ... Z15: =Z10/Z9 -> 255832.43
B17: Müşteri_Profil
B18: Eski Müşteri | M18: =M237+M240+M243+M246+M249+M252+M255 -> 24 | N18: =N237+N240+N243+N246+N249+N252+N255 -> 27 | O18: =O237+O240+O243+O246+O249+O252+O255 -> 37 | P18: =P237+P240+P243+P246+P249+P252+P255 -> 29 | Q18: =Q237+Q240+Q243+Q246+Q249+Q252+Q255 -> 36 | R18: =R237+R240+R243+R246+R249+R252+R255 -> 31 | S18: =S237+S240+S243+S246+S249+S252+S255 -> 30 | T18: =T237+T240+T243+T246+T249+T252+T255 -> 31 | ... Z18: =Z237+Z240+Z243+Z246+Z249+Z252+Z255 -> 33
B19: Yeni Müşteri | M19: =M236+M239+M242+M245+M248+M251+M254 -> 30 | N19: =N236+N239+N242+N245+N248+N251+N254 -> 23 | O19: =O236+O239+O242+O245+O248+O251+O254 -> 32 | P19: =P236+P239+P242+P245+P248+P251+P254 -> 20 | Q19: =Q236+Q239+Q242+Q245+Q248+Q251+Q254 -> 33 | R19: =R236+R239+R242+R245+R248+R251+R254 -> 31 | S19: =S236+S239+S242+S245+S248+S251+S254 -> 32 | T19: =T236+T239+T242+T245+T248+T251+T254 -> 31 | ... Z19: =Z236+Z239+Z242+Z245+Z248+Z251+Z254 -> 15
B20: Mağaza Walk In Müşterisi
B21: Kendi Bulduğumuz Müşteri
B22: Partner(Mimar)
B24: Kurumsal Satış(Kontrat)
B25: Satış Departmanı Kişi Sayısı | M25: 4 | N25: 4 | O25: 4 | P25: 4 | Q25: 4 | R25: 4 | S25: 4 | T25: 4 | U25: 4 | V25: 4 | W25: 4 | X25: 4 | Y25: 4 | Z25: 4
B26: Toplam Satış_Miktarı | M26: =sum(M80:M83) -> 1459275 | N26: =sum(N80:N83) -> 781163.93 | O26: =sum(O80:O83) -> 732093 | P26: =sum(P80:P83) -> 1166503 | Q26: =sum(Q80:Q83) -> 643089 | R26: =sum(R80:R83) -> 473637 | S26: =sum(S80:S83) -> 1981194 | T26: =sum(T80:T83) -> 323951 | ... Z26: =sum(Z80:Z83) -> 1436048
B27: Toplam Satış adeti | M27: =sum(M106:M109) -> 22 | N27: =sum(N106:N109) -> 18 | O27: =sum(O106:O109) -> 24 | P27: =sum(P106:P109) -> 23 | Q27: =sum(Q106:Q109) -> 24 | R27: =sum(R106:R109) -> 17 | S27: =sum(S106:S109) -> 28 | T27: =sum(T106:T109) -> 15 | ... Z27: =sum(Z106:Z109) -> 21
B28: Toplam Müşteri Sayısı | M28: =(M265+M266+M268+M269+M271+M272+M274+M275) -> 21 | N28: =(N265+N266+N268+N269+N271+N272+N274+N275) -> 18 | O28: =(O265+O266+O268+O269+O271+O272+O274+O275) -> 23 | P28: =(P265+P266+P268+P269+P271+P272+P274+P275) -> 21 | Q28: =(Q265+Q266+Q268+Q269+Q271+Q272+Q274+Q275) -> 20 | R28: =(R265+R266+R268+R269+R271+R272+R274+R275) -> 16 | S28: =(S265+S266+S268+S269+S271+S272+S274+S275) -> 27 | T28: =(T265+T266+T268+T269+T271+T272+T274+T275) -> 15 | ... Z28: =(Z265+Z266+Z268+Z269+Z271+Z272+Z274+Z275) -> 14
B29: Toplam Yeni Müşteri Sayısı | M29: =M265+M268+M271+M274 -> 7 | N29: =N265+N268+N271+N274 -> 7 | O29: =O265+O268+O271+O274 -> 11 | P29: =P265+P268+P271+P274 -> 13 | Q29: =Q265+Q268+Q271+Q274 -> 11 | R29: =R265+R268+R271+R274 -> 10 | S29: =S265+S268+S271+S274 -> 14 | T29: =T265+T268+T271+T274 -> 9 | ... Z29: =Z265+Z268+Z271+Z274 -> 4
B30: Yeni Müşteri Oranı | M30: =M29/M28 -> 0.33333333 | N30: =N29/N28 -> 0.38888889 | O30: =O29/O28 -> 0.47826087 | P30: =P29/P28 -> 0.61904762 | Q30: =Q29/Q28 -> 0.55 | R30: =R29/R28 -> 0.625 | S30: =S29/S28 -> 0.51851852 | T30: =T29/T28 -> 0.6 | ... Z30: =Z29/Z28 -> 0.28571429
B31: Ortalama Sepet Değeri | M31: =M26/M25 -> 364818.75 | N31: =N26/N25 -> 195290.98 | O31: =O26/O25 -> 183023.25 | P31: =P26/P25 -> 291625.75 | Q31: =Q26/Q25 -> 160772.25 | R31: =R26/R25 -> 118409.25 | S31: =S26/S25 -> 495298.5 | T31: =T26/T25 -> 80987.75 | ... Z31: =Z26/Z25 -> 359012
B33: Müşteri_Profil
B34: Eski Müşteri | M34: =(M266+M269+M272+M275) -> 14 | N34: =(N266+N269+N272+N275) -> 11 | O34: =(O266+O269+O272+O275) -> 12 | P34: =(P266+P269+P272+P275) -> 8 | Q34: =(Q266+Q269+Q272+Q275) -> 9 | R34: =(R266+R269+R272+R275) -> 6 | S34: =(S266+S269+S272+S275) -> 13 | T34: =(T266+T269+T272+T275) -> 6 | ... Z34: =(Z266+Z269+Z272+Z275) -> 10
B35: Yeni Müşteri | M35: =(M265+M268+M271+M274) -> 7 | N35: =(N265+N268+N271+N274) -> 7 | O35: =(O265+O268+O271+O274) -> 11 | P35: =(P265+P268+P271+P274) -> 13 | Q35: =(Q265+Q268+Q271+Q274) -> 11 | R35: =(R265+R268+R271+R274) -> 10 | S35: =(S265+S268+S271+S274) -> 14 | T35: =(T265+T268+T271+T274) -> 9 | ... Z35: =(Z265+Z268+Z271+Z274) -> 4
B36: Mağaza Walk In Müşterisi
B37: Kendi Bulduğumuz Müşteri
B38: Partner(Mimar)
B40: Aydınlatma
B41: Satış Departmanı Kişi Sayısı | M41: 5 | N41: 5 | O41: 5 | P41: 5 | Q41: 4 | R41: 4 | S41: 4 | T41: 4 | U41: 4 | V41: 4 | W41: 4 | X41: 4 | Y41: 4 | Z41: 4
B42: Toplam Satış_Miktarı | M42: =sum(M86:M89) -> 491879.34 | N42: =sum(N86:N89) -> 790041.89 | O42: =sum(O86:O89) -> 374298.77 | P42: =sum(P86:P89) -> 427805.55 | Q42: =sum(Q86:Q89) -> 501227.45 | R42: =sum(R86:R89) -> 439259.98 | S42: =sum(S86:S89) -> 379764.73 | T42: =sum(T86:T89) -> 813659.04 | ... Z42: =sum(Z86:Z89) -> 426049.25
B43: Toplam Satış adeti | M43: =(M218+M219+M221+M222+M224+M225+M227+M228) -> 25 | N43: =(N218+N219+N221+N222+N224+N225+N227+N228) -> 22 | O43: =(O218+O219+O221+O222+O224+O225+O227+O228) -> 28 | P43: =(P218+P219+P221+P222+P224+P225+P227+P228) -> 31 | Q43: =(Q218+Q219+Q221+Q222+Q224+Q225+Q227+Q228) -> 45 | R43: =(R218+R219+R221+R222+R224+R225+R227+R228) -> 40 | S43: =(S218+S219+S221+S222+S224+S225+S227+S228) -> 34 | T43: =(T218+T219+T221+T222+T224+T225+T227+T228) -> 27 | ... Z43: =(Z218+Z219+Z221+Z222+Z224+Z225+Z227+Z228) -> 58
B44: Toplam Müşteri Sayısı
B45: Ortalama Sepet Değeri | M45: =M42/M41 -> 98375.868 | N45: =N42/N41 -> 158008.38 | O45: =O42/O41 -> 74859.754 | P45: =P42/P41 -> 85561.11 | Q45: =Q42/Q41 -> 125306.86 | R45: =R42/R41 -> 109814.99 | S45: =S42/S41 -> 94941.182 | T45: =T42/T41 -> 203414.76 | ... Z45: =Z42/Z41 -> 106512.31
B47: Müşteri_Profil
B48: Eski Müşteri
B49: Yeni Müşteri
B50: Mağaza Walk In Müşterisi
B51: Kendi Bulduğumuz Müşteri
B52: Partner(Mimar)
B54: Marketing
B55: Satış Departmanı Kişi Sayısı | M55: 1 | N55: 1 | O55: 1 | P55: 1 | Q55: 1 | R55: 1 | S55: 1 | T55: 1 | U55: 1 | V55: 1 | W55: 1 | X55: 1 | Y55: 1 | Z55: 1 | AA55: 1
B56: Toplam Satış_Miktarı | M56: =244692/45 -> 5437.6 | N56: =508456/45 -> 11299.022 | O56: =424408/45 -> 9431.2889 | P56: =537113/45 -> 11935.844 | Q56: =520113/45 -> 11558.067 | R56: =263599/45 -> 5857.7556 | S56: =710706/45 -> 15793.467 | T56: =314623/45 -> 6991.6222 | U56: =389903/45 -> 8664.5111 | V56: =543876/45 -> 12086.133 | W56: 10320 | X56: 62043 | Y56: 26986 | Z56: 24868 | AA56: 35247
B57: Toplam Satış adeti | M57: 19 | N57: 27 | O57: 26 | P57: 25 | Q57: 20 | R57: 15 | S57: 24 | T57: 18 | U57: 17 | V57: 29 | W57: 29 | X57: 29 | Y57: 85 | Z57: 42 | AA57: 49
B58: Toplam Müşteri Sayısı | M58: 19 | N58: 27 | O58: 26 | P58: 25 | Q58: 20 | R58: 15 | S58: 24 | T58: 18 | U58: 17 | V58: 29 | W58: 29 | X58: 85 | Y58: 75 | Z58: 38 | AA58: 45
B59: Sales Per Rep | M59: =M56/M55 -> 5437.6 | N59: =N56/N55 -> 11299.022 | O59: =O56/O55 -> 9431.2889 | P59: =P56/P55 -> 11935.844 | Q59: =Q56/Q55 -> 11558.067 | R59: =R56/R55 -> 5857.7556 | S59: =S56/S55 -> 15793.467 | T59: =T56/T55 -> 6991.6222 | ... X59: =X56/X55 -> 62043 | Y59: 26986 | Z59: 24868 | AA59: 35247
B61: Müşteri_Profil
B62: Eski Müşteri | M62: 10 | N62: =23-18 -> 5 | O62: =24-O63 -> 3 | P62: =25-P63 -> 7 | Q62: =16-Q63 -> 3 | R62: =9-R63 -> 3 | S62: =27-S63 -> 12 | T62: =14-T63 -> 1 | U62: =8-U63 -> 1 | V62: 0 | W62: 12 | X62: 18 | Y62: 13 | Z62: 10 | AA62: 12
B63: Yeni Müşteri | M63: 3 | N63: 18 | O63: 21 | P63: 18 | Q63: 13 | R63: 6 | S63: 15 | T63: 13 | U63: 7 | V63: 22 | W63: 16 | X63: 67 | Y63: 62 | Z63: 28 | AA63: 33
B64: Mağaza Walk In Müşterisi
B65: Kendi Bulduğumuz Müşteri
B66: Partner(Mimar)
A68: Temsilci Performansı_Satış Miktari | B68: Mağaza(Retail)
B69: Banu | M69: 275998 | N69: 347957 | O69: 320520 | P69: 140258 | Q69: 447101 | R69: 9956 | S69: 143847 | T69: 188529 | U69: 99095 | V69: 54039 | W69: 20227 | X69: 40250 | Y69: 332126 | Z69: 135106 | AA69: 276134 | AC69: =sum(Y69:AA77) -> 7259934
B70: İdil | M70: 522966 | N70: 304624 | O70: 75429 | P70: 156705 | Q70: 259843 | R70: 408895 | S70: 283717 | T70: 169125 | U70: 318317 | V70: 383228 | W70: 406592 | X70: 419397 | Y70: 498432 | Z70: =3385+6205+18066+13000+140374+7186+19326+5184+9067+3590+922+8521+217754+23455+4009 -> 480044 | AA70: 276134 | AC70: 4151711
B71: Sena | M71: 60320 | N71: 357261 | O71: 176517 | P71: 102906 | Q71: 245968 | R71: 315728 | S71: 218636 | T71: 346359 | U71: 924088 | V71: 360096 | W71: 348498 | X71: 566363 | Y71: 373167 | Z71: 332320 | AA71: 276134 | AC71: =AC70/AC69 -> 0.57186622
B72: Ceren | M72: 136212 | N72: 93099 | O72: 22553 | P72: 1010670 | Q72: 314717 | R72: 341146 | S72: 506888 | T72: 350933 | U72: 125485 | V72: 480896 | W72: 328400 | X72: 251995 | Y72: 378677 | Z72: 262491 | AA72: 276134
B73: Derin | M73: =sum(M134:M135) -> 144936 | N73: =sum(N134:N135) -> 79265 | O73: =sum(O134:O135) -> 435502 | P73: =sum(P134:P135) -> 255024 | Q73: =sum(Q134:Q135) -> 137107 | R73: =sum(R134:R135) -> 234543 | S73: =sum(S134:S135) -> 367933 | T73: =sum(T134:T135) -> 115932 | ... V73: =sum(V134:V135) -> 255090 | W73: =14500+2559+5433+6951+2839+8646+7360+17680+12551+6626+4140+26314 -> 115599 | X73: =9000+30770+100+12089+3651+1344+114+167+2994+1102+40000+242221 -> 343552 | Y73: =40000+6012+4835+7690+431+50960+2130+216711+210000+41000+10915+406693+39372+45000 -> 1081749 | Z73: =63607+21895+1166+79495+16573+41876+800+6806 -> 232218 | AA73: 276134
B74: Bener | M74: 311631 | N74: 322382 | O74: 140879 | P74: 136808 | Q74: 187451 | R74: 165919 | S74: 527731 | T74: 218220 | U74: 249626 | V74: 158706 | W74: 338578 | X74: 334197 | Y74: 312593 | Z74: 74063 | AA74: 276134
B75: Betül | M75: 118 | N75: 4121 | O75: 18881 | P75: 66031 | Q75: 215033 | R75: 9145 | S75: 155212 | T75: 5968 | U75: 6214 | V75: 62911 | W75: 18635 | X75: 112299 | Y75: 29777 | Z75: 99654 | AA75: 80455
B76: Aleyna | X76: 19876 | Y76: 75876 | Z76: 119411 | AA76: 276134
B77: Simge | Y77: 97183 | Z77: 55520 | AA77: 276134
B79: Kurumsal(Kontrat)
B80: Burçin | M80: 341978 | N80: 375052.93 | O80: 149700 | P80: 227156 | Q80: 94553 | R80: 77205 | S80: 592301 | T80: 4000 | U80: 0 | V80: 0 | W80: 6555 | X80: 2250667 | Y80: 33757 | Z80: 738038 | AA80: 44722
B81: Zeynep | M81: 1058109 | N81: 169751 | O81: 430168 | P81: 524520 | Q81: 473116 | R81: 286875 | S81: 675992 | T81: 91662 | U81: 174298 | V81: 16375 | W81: 483057 | X81: 579974.78 | Y81: 978556 | Z81: 586639
B82: Elif | M82: 59188 | N82: 186141 | O82: 127005 | P82: 391400 | Q82: 50454 | R82: 97532 | S82: 201538 | T82: 108276 | U82: 118695 | V82: 199506 | W82: 52825 | X82: 168394 | Y82: 76850 | Z82: 34035 | AA82: 232370
B83: İrem | M83: 0 | N83: 50219 | O83: 25220 | P83: 23427 | Q83: 24966 | R83: 12025 | S83: 511363 | T83: 120013 | U83: 20373 | V83: 103746 | W83: 130308 | X83: 49508 | Y83: 233596 | Z83: 77336
B85: Aydınlatma
B86: Biricik | M86: 296172.95 | N86: 663026.74 | O86: 217688.27 | P86: 320731.3 | Q86: 305782.2 | R86: 185328.23 | S86: 145553.23 | T86: 565084.96 | U86: 207034.15 | V86: 293202 | W86: 151930 | X86: 271854 | Y86: 242476 | Z86: 115012
B87: Artun | M87: 152939.39 | N87: 48249.15 | O87: 114163.5 | P87: 29917.25 | Q87: 61464.25 | R87: 160052.75 | S87: 59228.5 | T87: 97094.08 | U87: 116938 | V87: 38971.75 | W87: 103210 | X87: 118260.8 | Y87: 88721.25 | Z87: 220009
B88: Ecem | M88: 22934 | N88: 47549 | O88: 39910 | P88: 57487 | Q88: 81126 | R88: 69172 | S88: 110132 | T88: 76688 | U88: 164730 | V88: 38798 | W88: 66690 | X88: 121793 | Y88: 40158 | Z88: 51272
B89: Beliz | M89: 19833 | N89: 31217 | O89: 2537 | P89: 19670 | Q89: 52855 | R89: 24707 | S89: 64851 | T89: 74792 | U89: 30555 | V89: 36805 | W89: 39905 | X89: 36968 | Y89: 36038.25 | Z89: 39756.25
B91: Marketing
B92: Ceren | M92: =244692/45 -> 5437.6 | N92: =508456/45 -> 11299.022 | O92: =424408/45 -> 9431.2889 | P92: =537113/45 -> 11935.844 | Q92: =520113/45 -> 11558.067 | R92: =263599/45 -> 5857.7556 | S92: =710706/45 -> 15793.467 | T92: =314623/45 -> 6991.6222 | U92: =389903/45 -> 8664.5111 | V92: =543876/45 -> 12086.133 | W92: 10320 | X92: 62043 | Y92: 26.986 | Z92: 24868 | AA92: 35247
A94: Temsilci Performansı_Satış Adet | B94: Mağaza(Retail)_Satış Adet
B95: Banu | M95: 5 | N95: 8 | O95: 7 | P95: 6 | Q95: 13 | R95: 4 | S95: 7 | T95: 7 | U95: 10 | V95: 3 | W95: 3 | X95: 4 | Y95: 6 | Z95: 7
B96: İdil | M96: 20 | N96: 17 | O96: 11 | P96: 6 | Q96: 11 | R96: 12 | S96: 8 | T96: 13 | U96: 12 | V96: 8 | W96: 11 | X96: 6 | Y96: 12 | Z96: 15
B97: Sena | M97: 3 | N97: 10 | O97: 9 | P97: 7 | Q97: 11 | R97: 9 | S97: 16 | T97: 13 | U97: 0 | V97: 17 | W97: 20 | X97: 24 | Y97: 19 | Z97: 16
B98: Ceren | M98: 9 | N98: 5 | O98: 3 | P98: 7 | Q98: 8 | R98: 4 | S98: 4 | T98: 5 | U98: 5 | V98: 8 | W98: 3 | X98: 9 | Y98: 9 | Z98: 8
B99: Derin | M99: =sum(M248:M249) -> 7 | N99: =sum(N248:N249) -> 8 | O99: =sum(O248:O249) -> 16 | P99: =sum(P248:P249) -> 10 | Q99: =sum(Q248:Q249) -> 12 | R99: =sum(R248:R249) -> 13 | S99: =sum(S248:S249) -> 8 | T99: =sum(T248:T249) -> 9 | ... V99: =sum(V248:V249) -> 15 | W99: 12 | X99: 0 | Y99: =11 -> 11
B100: Bener | M100: 11 | N100: 8 | O100: 12 | P100: 7 | Q100: 13 | R100: 9 | S100: 15 | T100: 16 | U100: 17 | V100: 11 | W100: 14 | X100: 15 | Y100: 19 | Z100: 8
B101: Betül | M101: 1 | N101: 7 | O101: 13 | P101: 24 | Q101: 54 | R101: 6 | S101: 31 | T101: 2 | U101: 2 | V101: 8 | W101: 10 | X101: 29 | Y101: 18 | Z101: 22 | AA101: 23
B102: Aleyna | X102: 4 | Y102: 2 | Z102: 3
B103: Simge | Y103: 15 | Z103: 9
B105: Kurumsal(Kontrat)
B106: Burçin | M106: 5 | N106: 3 | O106: 2 | P106: 5 | Q106: 3 | R106: 4 | S106: 3 | T106: 1 | U106: 0 | V106: 0 | W106: 2 | X106: 4 | Y106: 3 | Z106: 2 | AA106: 3
B107: Zeynep | M107: 9 | N107: 5 | O107: 11 | P107: 12 | Q107: 10 | R107: 7 | S107: 6 | T107: 4 | U107: 4 | V107: 4 | W107: 9 | X107: 8 | Y107: 11 | Z107: 8
B108: Elif | M108: 8 | N108: 6 | O108: 6 | P108: 6 | Q108: 7 | R108: 3 | S108: 6 | T108: 5 | U108: 5 | V108: 7 | W108: 3 | X108: 8 | Y108: 7 | Z108: 4 | AA108: 9
B109: İrem | N109: 4 | O109: 5 | Q109: 4 | R109: 3 | S109: 13 | T109: 5 | U109: 6 | V109: 7 | W109: 9 | X109: 7 | Y109: 8 | Z109: 7
B111: Aydınlatma
B112: Biricik | M112: 36 | N112: 24 | O112: 39 | P112: 25 | Q112: 25 | R112: 24 | S112: 16 | T112: 34 | U112: 28 | V112: 24 | W112: 18 | X112: 31 | Y112: 29 | Z112: 17
B113: Artun | M113: 11 | N113: 7 | O113: 16 | P113: 10 | Q113: 10 | R113: 12 | S113: 11 | T113: 11 | U113: 18 | V113: 7 | W113: 12 | X113: 14 | Y113: 10 | Z113: 18
B114: Ecem | M114: 6 | N114: 10 | O114: 11 | P114: 12 | Q114: 22 | R114: 18 | S114: 17 | T114: 9 | U114: 17 | V114: 10 | W114: 11 | X114: 25 | Y114: 9 | Z114: 7
B115: Beliz | M115: 8 | N115: 5 | O115: 1 | P115: 9 | Q115: 14 | R115: 10 | S115: 6 | T115: 7 | U115: 8 | V115: 17 | W115: 5 | X115: 9 | Y115: 12 | Z115: 16
...

Sheet Revenue Charts
A1: Sales Funnel
B2: Retail | C2: 45682 | D2: 45713 | E2: 45741 | F2: 45772 | G2: 45802 | H2: 45833 | I2: 45863 | J2: 45894 | K2: 45925 | L2: 45955 | M2: 45986 | N2: 46016
A3: Revenue | C3: ='Satış Departman Verisi'!M10 -> 1452181 | D3: ='Satış Departman Verisi'!N10 -> 1508709 | E3: ='Satış Departman Verisi'!O10 -> 1190281 | F3: ='Satış Departman Verisi'!P10 -> 1868402 | G3: ='Satış Departman Verisi'!Q10 -> 1807220 | H3: ='Satış Departman Verisi'!R10 -> 1485332 | I3: ='Satış Departman Verisi'!S10 -> 2203964 | J3: ='Satış Departman Verisi'!T10 -> 1395066 | ... M3: ='Satış Departman Verisi'!W10 -> 1576529
B7: Enterprise | C7: 45682 | D7: 45713 | E7: 45741 | F7: 45772 | G7: 45802 | H7: 45833 | I7: 45863 | J7: 45894 | K7: 45925 | L7: 45955 | M7: 45986 | N7: 46016
A8: Revenue | C8: ='Satış Departman Verisi'!M26 -> 1459275 | D8: ='Satış Departman Verisi'!N26 -> 781163.93 | E8: ='Satış Departman Verisi'!O26 -> 732093 | F8: ='Satış Departman Verisi'!P26 -> 1166503 | G8: ='Satış Departman Verisi'!Q26 -> 643089 | H8: ='Satış Departman Verisi'!R26 -> 473637 | I8: ='Satış Departman Verisi'!S26 -> 1981194 | J8: ='Satış Departman Verisi'!T26 -> 323951 | ... L8: ='Satış Departman Verisi'!V26 -> 319627
B12: Lighting | C12: 45682 | D12: 45713 | E12: 45741 | F12: 45772 | G12: 45802 | H12: 45833 | I12: 45863 | J12: 45894 | K12: 45925 | L12: 45955 | M12: 45986 | N12: 46016
C13: ='Satış Departman Verisi'!M42 -> 491879.34 | D13: ='Satış Departman Verisi'!N42 -> 790041.89 | E13: ='Satış Departman Verisi'!O42 -> 374298.77 | F13: ='Satış Departman Verisi'!P42 -> 427805.55 | G13: ='Satış Departman Verisi'!Q42 -> 501227.45 | H13: ='Satış Departman Verisi'!R42 -> 439259.98 | I13: ='Satış Departman Verisi'!S42 -> 379764.73 | J13: ='Satış Departman Verisi'!T42 -> 813659.04 | ... M13: ='Satış Departman Verisi'!W42 -> 361735
B16: Marketing | C16: 45682 | D16: 45713 | E16: 45741 | F16: 45772 | G16: 45802 | H16: 45833 | I16: 45863 | J16: 45894 | K16: 45925 | L16: 45955 | M16: 45986 | N16: 46016
A17: Revenue | C17: ='Satış Departmanı Verisi'!C46 -> 10592.83 | D17: ='Satış Departmanı Verisi'!D46 -> 5098 | E17: ='Satış Departmanı Verisi'!E46 -> 8841 | F17: ='Satış Departmanı Verisi'!F46 -> 11190 | G17: ='Satış Departmanı Verisi'!G46 -> 10844 | H17: ='Satış Departmanı Verisi'!H46 -> 3811 | I17: ='Satış Departmanı Verisi'!I46 -> 14360 | J17: ='Satış Departmanı Verisi'!J46 -> 8123 | ... M17: ='Satış Departmanı Verisi'!M46

Sheet Total Sales  Revenue Chart
A27: Veri
A28: 2015 | B28: 2016 | C28: 2017 | D28: 2018 | E28: 2019 | F28: 2020 | G28: 2021 | H28: 2022 | I28: 2023 | J28: 2024 | K28: 2025
A29: 13882589 | B29: 7111065 | C29: 10060317 | D29: 9817554 | E29: 8035913 | F29: 12854873 | G29: 11246016 | H29: 15938774 | I29: 19580773 | J29: 28260753 | K29: =#REF! -> #REF!

Sheet Per Person
A1: Total Sales
A2: Banu | B2: =#REF! -> #REF!
A3: İdil | B3: =#REF! -> #REF!
A4: Sena | B4: =#REF! -> #REF!
A5: Ceren | B5: =#REF! -> #REF!
A6: Derin | B6: =#REF! -> #REF!
A7: Bener | B7: =#REF! -> #REF!
A8: Betül | B8: =#REF! -> #REF!
A10: Kurumsal(Kontrat) | B10: =#REF! -> #REF!
A11: Burçin | B11: =#REF! -> #REF!
A12: Zeynep | B12: =#REF! -> #REF!
A13: Elif | B13: =#REF! -> #REF!
A14: İrem | B14: =#REF! -> #REF!
... A23: Ceren | B23: =#REF! -> #REF!
B24: =#REF! -> #REF!

Sheet Satış Departmanı Verisi
C1: 45658 | D1: 45659 | E1: 45660 | F1: 45661 | G1: 45662 | H1: 45663 | I1: 45664 | J1: 45665 | K1: 45666 | L1: 45667 | M1: 45668 | N1: 45669
A3: Toplam Gelir | C3: =C7+C20+C33+C46 -> 2957900.8 | D3: =D33+D46+D20+D7 -> 1714777.4 | E3: =E33+E46+E20+E7 -> 2320872 | F3: =F33+F46+F20+F7 -> 4269309 | G3: =G33+G46+G20+G7 -> 2867427 | H3: =H33+H46+H20+H7 -> 2421681 | I3: =I33+I46+I20+I7 -> 4572715 | J3: =J33+J46+J20+J7 -> 2402244 | K3: =K33+K46+K20+K7 -> 2961802 | L3: 2170000 | M3: 2170000 | N3: 2170000
A5: Departman Performansı | B5: Mağaza(Retail)
B6: Satış Departmanı Kişi Sayısı | C6: 8 | D6: 8 | E6: 8 | F6: 8 | G6: 7 | H6: 7 | I6: 7 | J6: 7 | K6: 7
B7: Toplam Satış_Miktarı | C7: =sum(C59:C65) -> 1445266 | D7: 1708601 | E7: 1208992 | F7: 2663810 | G7: 1706124 | H7: 1504993 | I7: 2197397 | J7: 1256025 | K7: 1992675
B8: Toplam Satış adeti | C8: =C13+C14 -> 5
B9: Toplam Müşteri Sayısı | C9: =C13+C14 -> 5
B10: Ortalama Sepet Değeri | C10: =C7/C6 -> 180658.25
B12: Müşteri_Profil
B13: Eski Müşteri | C13: 4
B14: Yeni Müşteri | C14: 1
B15: Mağaza Walk In Müşterisi
B16: Kendi Bulduğumuz Müşteri
B18: Kurumsal Satış(Kontrat)
B19: Satış Departmanı Kişi Sayısı | C19: 4 | D19: 4 | E19: 4 | F19: 4 | G19: 4 | H19: 4 | I19: 4 | J19: 4 | K19: 4
B20: Toplam Satış_Miktarı | C20: =sum(C68:C71) -> 1459275 | D20: 773.49 | E20: 726770 | F20: 1166503 | G20: 649901 | H20: 473617 | I20: 1981194 | J20: 324438 | K20: 438587
B21: Toplam Satış adeti
B22: Toplam Müşteri Sayısı
B23: Ortalama Sepet Değeri
D24: =D20/D19 -> 193.3725 | E24: =E20/E19 -> 181692.5 | F24: =F20/F19 -> 291625.75 | G24: =G20/G19 -> 162475.25 | H24: =H20/H19 -> 118404.25 | I24: =I20/I19 -> 495298.5 | J24: =J20/J19 -> 81109.5 | K24: =K20/K19 -> 109646.75
B25: Müşteri_Profil
B26: Eski Müşteri
B27: Yeni Müşteri
B28: Mağaza Walk In Müşterisi
B29: Kendi Bulduğumuz Müşteri
B31: Aydınlatma
B32: Satış Departmanı Kişi Sayısı | C32: 5 | D32: 5 | E32: 5 | F32: 5 | G32: 4 | H32: 4 | I32: 4 | J32: 4 | K32: 4
B33: Toplam Satış_Miktarı | C33: =sum(C74:C77) -> 42767 | D33: 304.868 | E33: 376269 | F33: 427806 | G33: 500558 | H33: 439260 | I33: 379764 | J33: 813658 | K33: 524126
B34: Toplam Satış adeti
B35: Toplam Müşteri Sayısı
B36: Ortalama Sepet Değeri
D37: =D33/D32 -> 60.9736 | E37: =E33/E32 -> 75253.8 | F37: =F33/F32 -> 85561.2 | G37: =G33/G32 -> 125139.5 | H37: =H33/H32 -> 109815 | I37: =I33/I32 -> 94941 | J37: =J33/J32 -> 203414.5 | K37: =K33/K32 -> 131031.5
B38: Müşteri_Profil
B39: Eski Müşteri
B40: Yeni Müşteri
B41: Mağaza Walk In Müşterisi
B42: Kendi Bulduğumuz Müşteri
B44: Marketing
B45: Satış Departmanı Kişi Sayısı | C45: 1 | D45: 1 | E45: 1 | F45: 1 | G45: 1 | H45: 1 | I45: 1 | J45: 1 | K45: 1
B46: Toplam Satış_Miktarı | C46: 10592.83 | D46: 5098 | E46: 8841 | F46: 11190 | G46: 10844 | H46: 3811 | I46: 14360 | J46: 8123 | K46: 6414
B47: Toplam Satış adeti
B48: Toplam Müşteri Sayısı
B49: Ortalama Sepet Değeri
D50: =D46/D45 -> 5098 | E50: =E46/E45 -> 8841 | F50: =F46/F45 -> 11190 | G50: =G46/G45 -> 10844 | H50: =H46/H45 -> 3811 | I50: =I46/I45 -> 14360 | J50: =J46/J45 -> 8123 | K50: =K46/K45 -> 6414
B51: Müşteri_Profil
B52: Eski Müşteri
B53: Yeni Müşteri
B54: Mağaza Walk In Müşterisi
B55: Kendi Bulduğumuz Müşteri
A58: Temsilci Performansı_Satış Miktari | B58: Mağaza(Retail)
B59: Banu | C59: 275998 | D59: 347871
B60: İdil | C60: 522966 | D60: 304624
B61: Sena | C61: 60320 | D61: 357261
B62: Ceren | C62: 136212 | D62: 96341
B63: Derin | C63: 138021 | D63: 84133
B64: Bener | C64: 311631 | D64: 322382
B65: Betül | C65: 118
B67: Kurumsal(Kontrat)
B68: Burçin | C68: 341978
B69: Zeynep | C69: 1058109
B70: Elif | C70: 59188
B71: İrem | C71: 0
B73: Aydınlatma
B74: Biricik | C74: 0
B75: Artun | C75: 0
B76: Ecem | C76: 22934
B77: Beliz | C77: 19833
B80: Marketing
B81: Ceren
A83: Temsilci Performansı_Satış Adet | B83: Mağaza(Retail)_Satış Geliri
B84: Banu | C84: 5
B85: İdil | C85: 20
B86: Sena | C86: 3
B87: Ceren | C87: 9
B88: Derin | C88: 6
B89: Bener | C89: 11
B90: Betül | C90: 1
B92: Kurumsal(Kontrat)
B93: Burçin | C93: 5
B94: Zeynep
B95: Elif
B96: İrem
B98: Aydınlatma
B99: Biricik
B100: Artun
B101: Ecem | C101: 6
B102: Beliz | C102: 8
B104: Marketing
B105: Ceren
A107: Temsilci Performansı_Satış Miktarı/Stok/Sipariş Krılımı | B107: Mağaza(Retail)_Satış Geliri
B108: Banu
A109: Stok | C109: 125389
A110: Sipariş | C110: 112167
B111: İdil
A112: Stok | C112: 122857
A113: Sipariş | C113: 399851
B114: Sena
A115: Stok | C115: 44392
A116: Sipariş | C116: 15928
B117: Ceren
...

Sheet Sheet26
A1: 2015 | B1: 2016 | C1: 2017 | D1: 2018 | E1: 2019 | F1: 2020 | G1: 2021 | H1: 2022 | I1: 2023 | J1: 2024 | K1: 2025
A2: 13882589 | B2: 7111065 | C2: 10060317 | D2: 9817554 | E2: 8035913 | F2: 12854873 | G2: 11246016 | H2: 15938774 | I2: 19580773 | J2: 28260753 | K2: =#REF! -> #REF!

Sheet Charts
E2: SALES DASHBOARD
B6: Retail
